Workbook

Sheet README
A1: Final Search, Selection, and PRISMA Supplement — Corpus n = 22
A3: Item | B3: Final status
A4: Final search date | B4: 2 September 2026
A5: Eligibility window | B5: January 2015 through 2 September 2026; no calendar-year 2025 cutoff
A6: Final coded corpus | B6: 22
A7: Database-derived inclusions | B7: 17
A8: Supplementary inclusions | B8: 5
A9: Original route | B9: 180 occurrences; 8 duplicates; 172 unique; 15 final inclusions after reassessment
A10: Sensitivity route | B10: 103 occurrences; 16 duplicates; 87 unique; 28 already assessed/included; 59 new; 0 new inclusions
A11: Final update route | B11: 76 occurrences; 17 duplicates; 59 unique; 20 already assessed; 39 new; 2 inclusions
A12: Scope | B12: Journal reviews in which RL and operational control/energy management of occupied residential or commercial buildings are central and separable. Grid-service, electricity-market, and EV-centered reviews are outside the quantitative scope.
A13: Deduplication | B13: Exact DOI followed by normalized-title matching (case, punctuation, accents, and whitespace removed).
A14: Route-neutral eligibility | B14: Discovery route was recorded for provenance but did not determine eligibility; every record was assessed against the same final criteria.
A15: Historical-stage limitation | B15: The contemporaneous split of the original 172 records between title/abstract exclusion and full-text exclusion was not retained. This workbook reports that original route as a combined eligibility-assessment stage rather than inventing counts.
A16: Reviewer involvement | B16: Screening was performed by a single reviewer. Inclusion eligibility for all 22 reviews was independently assessed by a co-author. Coding reliability was estimated on a stratified random subsample of six reviews (27%) coded independently by a co-author against the same decision rules: across 786 survey–dimension pairs, exact agreement 72.6%, agreement within one scale level 92.2%, linear-weighted Cohen's kappa 0.71 (see inter_rater_reliability_six_reviews.xlsx). Single-reviewer screening remains stated as a limitation in the manuscript.
A17: Prepared for | B17: Revision of EAI-D-26-00659

Sheet PRISMA Accounting
A1: Reconciled Route-Based PRISMA Accounting
A3: Route | B3: Raw occurrences | C3: Duplicate occurrences | D3: Previously assessed / already included | E3: Distinct records screened | F3: Included from route | G3: Excluded from route | H3: Known title/abstract exclusions | I3: Known full texts assessed | J3: Known full-text exclusions
A4: Original cumulative search | B4: 180 | C4: 8 | D4: 0 | E4: =B4-C4-D4 -> 172 | F4: 15 | G4: =E4-F4 -> 157 | H4: Not retained | I4: Not retained | J4: See close-exclusion register
A5: Expanded sensitivity | B5: 103 | C5: 16 | D5: 28 | E5: =B5-C5-D5 -> 59 | F5: 0 | G5: =E5-F5 -> 59 | H5: Not reported separately | I5: 1 close scope reassessment | J5: 1 (Sajid et al.)
A6: Final main-query update | B6: 76 | C6: 17 | D6: 20 | E6: =B6-C6-D6 -> 39 | F6: 2 | G6: =E6-F6 -> 37 | H6: 33 | I6: 6 | J6: 4
A7: Database-route totals | B7: =SUM(B4:B6) -> 359 | C7: =SUM(C4:C6) -> 41 | D7: =SUM(D4:D6) -> 48 | E7: =SUM(E4:E6) -> 270 | F7: =SUM(F4:F6) -> 17 | G7: =SUM(G4:G6) -> 253
A9: Final-corpus reconciliation | B9: Count
A10: Database-derived included reviews | B10: =F7 -> 17
A11: Supplementary included reviews | B11: 5
A12: Final coded corpus | B12: =B10+B11 -> 22
A13: Check | B13: =IF(B12=22,"PASS","CHECK") -> PASS
A15: Interpretive note | B15: Value
A16: Combined raw occurrences | B16: 359 across three distinct search routes; not a single undifferentiated database search
A17: Distinct database records actually screened | B17: 270 after route-specific deduplication and removal of records already assessed through earlier routes
A18: Historical stage reporting | B18: Original 172 are reported as one eligibility-assessment stage because the contemporaneous title/abstract versus full-text split was not preserved

Sheet Search Log
A1: Search Dates, Databases, and Verified Counts
A3: Route | B3: Database/export | C3: Search date | D3: Year filter | E3: Raw occurrences | F3: Unique after route deduplication | G3: Prior records removed | H3: Notes
A4: Original cumulative | B4: Web of Science | C4: 46197 | D4: 2015–2026-06-24 | E4: 56 | H4: Initial search 5 Feb 2025; cumulative export updated 24 Jun 2026
A5: Original cumulative | B5: ScienceDirect | C5: 46197 | D5: 2015–2026-06-24 | E5: 70 | H5: Initial search 5 Feb 2025; cumulative export updated 24 Jun 2026
A6: Original cumulative | B6: IEEE Xplore | C6: 46197 | D6: 2015–2026-06-24 | E6: 54 | H6: Initial search 5 Feb 2025; cumulative export updated 24 Jun 2026
A7: Original total | B7: All three | C7: 46197 | E7: 180 | F7: 172 | G7: 0 | H7: 8 duplicates removed
A8: Expanded sensitivity | B8: Web of Science | C8: 46265 | D8: 2015–2026 | E8: 60 | H8: Broader system-level domain terms
A9: Expanded sensitivity | B9: ScienceDirect A | C9: 46265 | D9: 2015–2026 | E9: 5 | H9: Boolean-limit split A
A10: Expanded sensitivity | B10: ScienceDirect B | C10: 46265 | D10: 2015–2026 | E10: 15 | H10: Boolean-limit split B
A11: Expanded sensitivity | B11: IEEE Xplore | C11: 46265 | D11: 2015–2026 | E11: 23 | H11: All publication types retained initially
A12: Sensitivity total | B12: All three | C12: 46265 | E12: 103 | F12: 87 | G12: 28 | H12: 16 duplicates; 25 original matches + Latoń + Michailidis + Sierla already in corpus; 59 new
A13: Final main-query update | B13: Web of Science | C13: 46267 | D13: 2025–2026 | E13: 26 | H13: Original main concept query rerun
A14: Final main-query update | B14: ScienceDirect A | C14: 46267 | D14: 2025–2026 | E14: 19 | H14: Boolean-limit split A
A15: Final main-query update | B15: ScienceDirect B | C15: 46267 | D15: 2025–2026 | E15: 16 | H15: Boolean-limit split B
A16: Final main-query update | B16: IEEE Xplore | C16: 46267 | D16: 2025–2026 | E16: 15 | H16: Original main concept query rerun
A17: Final update total | B17: All three | C17: 46267 | E17: 76 | F17: 59 | G17: 20 | H17: 17 duplicates; 12 original + 8 sensitivity records already assessed; 39 new

Sheet Search Strings
A1: Database-Specific Search Strings and Filters
A3: Route | B3: Database | C3: Fields | D3: Exact query / implementation | E3: Filters | F3: Provenance note
A4: Original + final update | B4: Web of Science | C4: Topic (TS) + Title (TI) | D4: TS=(("reinforcement learning" OR "deep reinforcement learning" OR "multi-agent reinforcement learning") AND ("building automation" OR "building energy management" OR "home energy management" OR "HVAC" OR "smart building" OR "building energy" OR "thermal comfort")) AND TI=(review OR survey OR overview OR "systematic literature review") | E4: English; 2015–24 Jun 2026 cumulatively; rerun for 2025–2 Sep 2026 | F4: Historical export does not embed query history; syntax reproduces the manuscript-recorded concept blocks
A5: Original + final update | B5: IEEE Xplore | C5: All Metadata + Document Title | D5: (("reinforcement learning" OR "deep reinforcement learning" OR "multi-agent reinforcement learning")) AND (("building automation" OR "building energy management" OR "home energy management" OR "HVAC" OR "smart building" OR "building energy" OR "thermal comfort")) AND (Document Title: review OR survey OR overview OR "systematic literature review") | E5: English; 2015–24 Jun 2026 cumulatively; rerun for 2025–2 Sep 2026 | F5: Platform-compatible transcription of the recorded concept blocks
A6: Original + final update A | B6: ScienceDirect | C6: Title/abstract/keywords + Title | D6: ("reinforcement learning" OR "deep reinforcement learning" OR "multi-agent reinforcement learning") AND ("building automation" OR "building energy management" OR "home energy management" OR "HVAC"); Title: review OR survey OR overview OR "systematic literature review" | E6: English; relevant date range | F6: Split to respect the maximum-eight-connectors limit per field
A7: Original + final update B | B7: ScienceDirect | C7: Title/abstract/keywords + Title | D7: ("reinforcement learning" OR "deep reinforcement learning" OR "multi-agent reinforcement learning") AND ("smart building" OR "building energy" OR "thermal comfort"); Title: review OR survey OR overview OR "systematic literature review" | E7: English; relevant date range | F7: Split to respect the maximum-eight-connectors limit per field
A8: Expanded sensitivity | B8: Web of Science | C8: Topic (TS) + Title (TI) | D8: TS=((("reinforcement learning" OR "deep reinforcement learning" OR "multi-agent reinforcement learning")) AND ("building cluster*" OR "multi-building*" OR "multiple building*" OR "district heating" OR "district energy" OR "district cooling" OR "energy communit*" OR "building microgrid*" OR "grid-interactive building*" OR "grid-responsive building*" OR "demand response")) AND TI=(review OR survey OR overview OR "systematic literature review") | E8: English; 2015–2026 | F8: Exact recorded sensitivity query
A9: Expanded sensitivity | B9: IEEE Xplore | C9: All Metadata + Document Title | D9: ("All Metadata":"reinforcement learning" OR "All Metadata":"deep reinforcement learning" OR "All Metadata":"multi-agent reinforcement learning") AND ("All Metadata":"building cluster*" OR "All Metadata":"multi-building*" OR "All Metadata":"multiple building*" OR "All Metadata":"district heating" OR "All Metadata":"district energy" OR "All Metadata":"district cooling" OR "All Metadata":"energy communit*" OR "All Metadata":"building microgrid*" OR "All Metadata":"grid-interactive building*" OR "All Metadata":"grid-responsive building*" OR "All Metadata":"demand response") AND ("Document Title":review OR "Document Title":survey OR "Document Title":overview OR "Document Title":"systematic literature review") | E9: English; 2015–2026 | F9: Exact recorded sensitivity query
A10: Expanded sensitivity A | B10: ScienceDirect | C10: Title/abstract/keywords + Title | D10: ("reinforcement learning" OR "deep reinforcement learning" OR "multi-agent reinforcement learning") AND ("building cluster" OR "multi-building" OR "multiple building" OR "district heating" OR "district energy" OR "district cooling"); Title: review OR survey OR overview OR "systematic literature review" | E10: English; 2015–2026 | F10: Exact recorded query A
A11: Expanded sensitivity B | B11: ScienceDirect | C11: Title/abstract/keywords + Title | D11: ("reinforcement learning" OR "deep reinforcement learning" OR "multi-agent reinforcement learning") AND ("energy community" OR "building microgrid" OR "grid-interactive building" OR "grid-responsive building" OR "demand response"); Title: review OR survey OR overview OR "systematic literature review" | E11: English; 2015–2026 | F11: Exact recorded query B

Sheet Eligibility Codebook
A1: Final Eligibility Criteria and Decision Rules
A3: Dimension | B3: Include when | C3: Exclude when | D3: Evidence checked | E3: Primary exclusion label | F3: Final scope clarification
A4: Publication type | B4: Full peer-reviewed journal review, survey, systematic review, or comprehensive review | C4: Primary study, conference paper, chapter, thesis, report, preprint, corrigendum, letter, or short non-review format | D4: Article type, venue, length, review structure | E4: Wrong publication type | F4: Contextual records may be discussed but are not coded
A5: Language/access | B5: English full text accessible | C5: Non-English or full text unavailable | D5: Full text and bibliographic record | E5: Language/full text unavailable | F5: No eligible record was excluded solely by publication year
A6: RL centrality | B6: RL/DRL/MARL organizes the objectives, study selection, taxonomy, comparisons, or synthesis | C6: RL is one method in a broader AI, ML, optimization, MPC, or control review | D6: Objectives, eligibility, tables, taxonomy, proportion devoted to RL | E6: RL not central | F6: A prominent RL paragraph alone is insufficient
A7: Building-control centrality | B7: Control or energy management of occupied residential or commercial buildings is a central and separable review domain | C7: Grid, markets, EVs, industrial systems, agriculture, or general control dominate | D7: Research questions, taxonomy, included-study distribution | E7: Building control not central | F7: Buildings must be explicit controllable units
A8: Included subsystems | B8: HVAC, thermal comfort, HEMS/BEMS, lighting, storage, renewables, BIPV, occupant-centric control | C8: Occupant modelling without a control decision; non-building assets | D8: State/action/objective and application scope | E8: Outside building-control scope | F8: Multi-building/district work qualifies only when building-control findings are separable
A9: Grid interaction boundary | B9: Building-side control remains central; grid signal is an input or constraint | C9: Grid services, market participation, or power-system operation is the principal synthesis | D9: System boundary and controlled resources | E9: Outside declared grid scope | F9: The final quantitative corpus intentionally excludes grid-interaction reviews centered on grid services
A10: Independence | B10: Distinct review and evidence base | C10: Duplicate, corrigendum, or substantially overlapping synthesis | D10: Authors, abstract, tables, primary-study set | E10: Duplicate/overlapping review | F10: Two applications. The Mazhar Next Energy record is excluded in favour of the independent IET review. Han et al. (2019), Sustainable Cities and Society 51:101748, is excluded as a companion report of the same review programme as the included Han et al. (2021): the 2021 review states which primary studies it excludes and refers the reader to the 2019 review for them, so the two partition a single evidence base. The criterion is triggered by a declared partition of the evidence base, not by shared authorship alone; Li et al. (2025) and Lei et al. (2026) share three authors but select on orthogonal axes and neither refers excluded literature to the other, so both are retained.
A11: Date | B11: Published and available by 2 September 2026 | C11: Available only after the final search date | D11: Online publication/index date | E11: Outside date window | F11: Eligibility begins January 2015; no December 2025 cutoff

Sheet Included 22
A1: Final Included Review Corpus (n = 22)
A3: Corpus ID | B3: Title | C3: Authors | D3: Year | E3: Venue | F3: DOI | G3: Inclusion route | H3: Corpus status | I3: Database-derived? | J3: Inclusion rationale
A4: INC-01 | B4: A review of reinforcement learning for autonomous building energy management | C4: Mason, Karl; Grijalva, Santiago | D4: 2019 | E4: Computers & Electrical Engineering | F4: 10.1016/j.compeleceng.2019.07.019 | G4: Original database search | H4: Pre-existing corpus | I4: Yes | J4: Eligible journal review with RL and operational building control or energy management as central and separable subjects.
A5: INC-02 | B5: The reinforcement learning method for occupant behavior in building control: A review | C5: Han, Mengjie; Zhao, Jing; Zhang, Xingxing; Shen, Jingchun; Li, Yu | D5: 2021 | E5: Energy and Built Environment | F5: 10.1016/j.enbenv.2020.08.005 | G5: Original database search | H5: Pre-existing corpus | I5: Yes | J5: Eligible journal review with RL and operational building control or energy management as central and separable subjects.
A6: INC-03 | B6: Reinforcement learning for building controls: The opportunities and challenges | C6: Wang, Zhe; Hong, Tianzhen | D6: 2020 | E6: Applied Energy | F6: 10.1016/j.apenergy.2020.115036 | G6: Original database search | H6: Pre-existing corpus | I6: Yes | J6: Eligible journal review with RL and operational building control or energy management as central and separable subjects.
A7: INC-04 | B7: A Review of Deep Reinforcement Learning for Smart Building Energy Management | C7: Yu, L; Qin, SQ; Zhang, M; Shen, C; Jiang, T; Guan, XH | D7: 2021 | E7: IEEE INTERNET OF THINGS JOURNAL | F7: 10.1109/jiot.2021.3078462 | G7: Original database search | H7: Pre-existing corpus | I7: Yes | J7: Eligible journal review with RL and operational building control or energy management as central and separable subjects.
A8: INC-05 | B8: A review of reinforcement learning applications to control of heating, ventilation and air conditioning systems | C8: Sierla, Seppo; Ihasalo, Heikki; Vyatkin, Valeriy | D8: 2022 | E8: Energies | F8: 10.3390/en15103526 | G8: Supplementary/citation searching; later retrieved by sensitivity search | H8: Pre-existing corpus; provenance corrected | I8: No | J8: Eligible journal review with RL and HVAC control as central and separable subjects.
A9: INC-06 | B9: Applications of reinforcement learning for building energy efficiency control: A review | C9: Fu, Qiming; Han, Zhicong; Chen, Jianping; Lu, You; Wu, Hongjie; Wang, Yunzhe | D9: 2022 | E9: Journal of Building Engineering | F9: 10.1016/j.jobe.2022.104165 | G9: Original database search | H9: Pre-existing corpus | I9: Yes | J9: Eligible journal review with RL and operational building control or energy management as central and separable subjects.
A10: INC-07 | B10: Building Energy Management With Reinforcement Learning and Model Predictive Control: A Survey | C10: H. Zhang; S. Seal; D. Wu; F. Bouffard; B. Boulet | D10: 2022 | E10: IEEE Access | F10: 10.1109/access.2022.3156581 | G10: Original database search | H10: Pre-existing corpus | I10: Yes | J10: Eligible journal review with RL and operational building control or energy management as central and separable subjects.
A11: INC-08 | B11: Reinforcement Learning: Theory and Applications in HEMS | C11: Al-Ani, O; Das, S | D11: 2022 | E11: ENERGIES | F11: 10.3390/en15176392 | G11: Original database search | H11: Pre-existing corpus | I11: Yes | J11: Eligible journal review with RL and operational building control or energy management as central and separable subjects.
A12: INC-09 | B12: Systematic Review on Deep Reinforcement Learning-Based Energy Management for Different Building Types | C12: Shaqour, Ayas; Hagishima, Aya | D12: 2022 | E12: Energies | F12: 10.3390/en15228663 | G12: Supplementary Google Scholar search | H12: Pre-existing corpus | I12: No | J12: Eligible journal review with RL and building energy management as central and separable subjects.
A13: INC-10 | B13: A Review of Reinforcement Learning for Controlling Building Energy Systems From a Computer Science Perspective | C13: Weinberg, David; Wang, Qian; Timoudas, Thomas Ohlson; Fischione, Carlo | D13: 2023 | E13: Sustainable Cities and Society | F13: 10.1016/j.scs.2022.104351 | G13: Original database search | H13: Pre-existing corpus | I13: Yes | J13: Eligible journal review with RL and operational building control or energy management as central and separable subjects.
A14: INC-11 | B14: Dynamic indoor thermal environment using Reinforcement Learning-based controls: Opportunities and challenges | C14: Chatterjee, Arnab; Khovalyg, Dolaana | D14: 2023 | E14: Building and Environment | F14: 10.1016/j.buildenv.2023.110766 | G14: Original database search | H14: Pre-existing corpus | I14: Yes | J14: Eligible journal review with RL and operational building control or energy management as central and separable subjects.
A15: INC-12 | B15: An overview of reinforcement learning-based approaches for smart home energy management systems with energy storages | C15: Pinthurat, W; Surinkaew, T; Hredzak, B | D15: 2024 | E15: RENEWABLE & SUSTAINABLE ENERGY REVIEWS | F15: 10.1016/j.rser.2024.114648 | G15: Original database search | H15: Pre-existing corpus | I15: Yes | J15: Eligible journal review with RL and operational building control or energy management as central and separable subjects.
... A25: INC-22 | B25: Hybrid Reinforcement Learning for occupant-centric building control: A review and deployment framework for co-optimizing energy, comfort, and indoor air quality | C25: Mohsenpour, Majid; Xing, Yangang | D25: 2026 | E25: Applied Energy | F25: 10.1016/j.apenergy.2026.127392 | G25: Supplementary publisher/citation searching | H25: Added during revision | I25: No | J25: RL structures the occupant-centric building-control review and deployment synthesis; energy, comfort, and indoor-air-quality control are the central building-side objectives.

Sheet Provenance 22
A1: Discovery Provenance of the 22 Included Reviews
A2: Export presence columns record whether the review appears in the preserved raw RIS exports for each route, verified by DOI and normalised-title matching against all eleven export files. They document retrievability, not the route through which the review was actually first obtained.
A4: Corpus ID | B4: Review | C4: Year | D4: DOI | E4: Documented discovery route | F4: Corpus status | G4: In original export | H4: In sensitivity export | I4: In final-update export | J4: Evidence basis for the stated route
A5: INC-01 | B5: Mason et al. (2019) | C5: 2019 | D5: 10.1016/j.compeleceng.2019.07.019 | E5: Original database search | F5: Pre-existing corpus | G5: Yes | H5: No | I5: No | J5: Present in the preserved original cumulative export (24 Jun 2026).
A6: INC-02 | B6: Han et al. (2021) | C6: 2021 | D6: 10.1016/j.enbenv.2020.08.005 | E6: Original database search | F6: Pre-existing corpus | G6: Yes | H6: No | I6: No | J6: Present in the preserved original cumulative export (24 Jun 2026), record ORI-059.
A7: INC-03 | B7: Wang et al. (2020) | C7: 2020 | D7: 10.1016/j.apenergy.2020.115036 | E7: Original database search | F7: Pre-existing corpus | G7: Yes | H7: No | I7: No | J7: Present in the preserved original cumulative export (24 Jun 2026).
A8: INC-04 | B8: Yu et al. (2021) | C8: 2021 | D8: 10.1109/jiot.2021.3078462 | E8: Original database search | F8: Pre-existing corpus | G8: Yes | H8: Yes | I8: No | J8: Present in the preserved original cumulative export (24 Jun 2026). Also returned by the sensitivity route.
A9: INC-05 | B9: Sierla et al. (2022) | C9: 2022 | D9: 10.3390/en15103526 | E9: Supplementary/citation searching; later retrieved by sensitivity search | F9: Pre-existing corpus; provenance corrected | G9: No | H9: Yes | I9: No | J9: Belonged to the pre-existing coded corpus but is absent from the preserved original export; the original discovery log was not retained and no specific backward-citation source is claimed. Independently retrieved by the 31 Aug 2026 sensitivity search (DOI 10.3390/en15103526, record SENS-036), which corroborates retrievability.
A10: INC-06 | B10: Fu et al. (2022) | C10: 2022 | D10: 10.1016/j.jobe.2022.104165 | E10: Original database search | F10: Pre-existing corpus | G10: Yes | H10: No | I10: No | J10: Present in the preserved original cumulative export (24 Jun 2026).
A11: INC-07 | B11: H. Zhang et al. (2022) | C11: 2022 | D11: 10.1109/access.2022.3156581 | E11: Original database search | F11: Pre-existing corpus | G11: Yes | H11: No | I11: No | J11: Present in the preserved original cumulative export (24 Jun 2026).
A12: INC-08 | B12: Al-Ani et al. (2022) | C12: 2022 | D12: 10.3390/en15176392 | E12: Original database search | F12: Pre-existing corpus | G12: Yes | H12: No | I12: No | J12: Present in the preserved original cumulative export (24 Jun 2026).
A13: INC-09 | B13: Shaqour et al. (2022) | C13: 2022 | D13: 10.3390/en15228663 | E13: Supplementary Google Scholar search | F13: Pre-existing corpus | G13: No | H13: No | I13: No | J13: Located during the original study using the same search concepts. Absent from all preserved exports and never re-retrieved by a later route; earliest documented route reported. Direct Google Scholar find, so no parent citation trail applies.
A14: INC-10 | B14: Weinberg et al. (2023) | C14: 2023 | D14: 10.1016/j.scs.2022.104351 | E14: Original database search | F14: Pre-existing corpus | G14: Yes | H14: Yes | I14: No | J14: Present in the preserved original cumulative export (24 Jun 2026). Also returned by the sensitivity route.
A15: INC-11 | B15: Chatterjee et al. (2023) | C15: 2023 | D15: 10.1016/j.buildenv.2023.110766 | E15: Original database search | F15: Pre-existing corpus | G15: Yes | H15: No | I15: No | J15: Present in the preserved original cumulative export (24 Jun 2026).
... A26: INC-22 | B26: Mohsenpour et al. (2026) | C26: 2026 | D26: 10.1016/j.apenergy.2026.127392 | E26: Supplementary publisher/citation searching | F26: Added during revision | G26: No | H26: No | I26: No | J26: Identified during revision through publisher and institutional searching. Absent from all preserved exports, consistent with publication after the 2 Sep 2026 export queries were framed; earliest documented route reported.
A28: Note on supplementary records
A29: For supplementary records whose original discovery log was not retained, the earliest documented route is reported. No specific backward-citation source is claimed where it could not be reconstructed.
A31: Summary
A32: Traceable to a preserved database export | B32: 20
A33: of which present in the original cumulative export | B33: 15
A34: of which present only in the final main-query update | B34: 2
A35: of which present only in the expanded sensitivity export | B35: 3
A36: Absent from every preserved export | B36: 2
A37: Database-derived per the inclusion route column | B37: 17
A38: Supplementary-route inclusions | B38: 5
A39: Total | B39: 22

Sheet Original 172
A1: Original Cumulative Search — 172 Unique Records
A3: Original ID | B3: Sources | C3: Occurrence count | D3: Title | E3: Authors | F3: Year | G3: Type | H3: Venue | I3: DOI | J3: Final decision | K3: Primary reason | L3: Assessment stage | M3: Decision note | N3: Source files | O3: Abstract
A4: ORI-045 | B4: Web of Science | C4: 1 | D4: A bibliometric analysis and review on reinforcement learning for transportation applications | E4: Li, C; Bai, L; Yao, LA; Waller, ST; Liu, W | F4: 2023 | G4: JOUR | H4: TRANSPORTMETRICA B-TRANSPORT DYNAMICS | I4: 10.1080/21680566.2023.2179461 | J4: Exclude | K4: Building control is not the central application domain | L4: Historical eligibility assessment | M4: The historical title/abstract versus full-text split was not retained; reason reconstructed from the final scope and available record metadata. | N4: wos_final.ris
A5: ORI-131 | B5: IEEE Xplore | C5: 1 | D5: A Comprehensive Review of Energy Management Strategies in Hybrid Electric Vehicles: Comparative Analysis and Challenges | E5: V. Chandra Tella; M. Alzayed; H. Chaoui | F5: 2024 | G5: JOUR | H5: IEEE Access | I5: 10.1109/access.2024.3509737 | J5: Exclude | K5: Reinforcement learning is not the central review subject | L5: Historical eligibility assessment | M5: The historical title/abstract versus full-text split was not retained; reason reconstructed from the final scope and available record metadata. | N5: ieee_final.ris | O5: As air pollution, greenhouse gases, and global warming worsen, finding clean energy sources is critical. Renewable energy is a promising solution, especially in the transportation sector, which consumes significant energy. Hybrid electric vehicles (HEVs), combining an internal combustion engine and an electric battery, are key to reducing fossil fuel use and mitigating environmental harm. Effectively managing power distribution between these sources to enhance efficiency and minimize fuel consumption is crucial, known as an Energy Management Strategy (EMS). This article provides an overview of various EMS approaches for HEVs, analyzing their advantages and disadvantages. Rule-based strategies offer simplicity, optimization-based strategies provide superior performance, and advanced techniques like machine learning promise significant improvements. Current trends include integrating sophisticated sensors, data analytics, and artificial intelligence for real-time decision-making. Future directions aim at robust EMS frameworks integrating smart grid technologies and vehicle-to-everything (V2X) communication. The article reviews EMS methodologies, comparing their strengths and weaknesses, and discusses the main challenges and future trends in energy management for hybrid electric vehicles.
A6: ORI-105 | B6: ScienceDirect | C6: 1 | D6: A comprehensive review of machine learning and IoT solutions for demand side energy management, conservation, and resilient operation | E6: Elsisi, Mahmoud; Amer, Mohammed; Dababat, Alya’; Su, Chun-Lien | F6: 2023 | G6: JOUR | H6: Energy | I6: 10.1016/j.energy.2023.128256 | J6: Exclude | K6: Reinforcement learning is not the central review subject | L6: Historical eligibility assessment | M6: The historical title/abstract versus full-text split was not retained; reason reconstructed from the final scope and available record metadata. | N6: ScienceDirect_citations_1783952383784(1).ris | O6: The energy consumption of major equipment in residential and industrial facilities can be minimized through a variety of cost-effective energy-saving measures. Most saving strategies are economically viable where several algorithms can be employed to reduce energy consumption to reduce costs to a considerable extent. Machine learning (ML) is one of these techniques. A review of recent research efforts concerning the application of ML strategies to energy conservation and management problems is presented in this study. In addition, ML approaches and strategies for energy-saving problems, management, technologies, and control methods have been discussed. A comprehensive review of all available publications is also used to make observations about past considerations. As a result, it has been concluded that ML is capable of solving a wide range of decision and management problems within a short period of time with minimal energy consumption. In addition, ML perspectives have been viewed from the perspective of emerging communication technologies, instruments, and cyber-physical systems (CPSs), along with the advancement of ultra-durable and energy-efficient Internet-of-Things (IoT) based communication sensors technology. Moreover, a comprehensive review of recent developments in ML algorithms is also included, including safe reinforcement learning (RL), Deep RL, path integral control for RL, and others not previously. Lastly, critical ML considerations such as emergency and remedial measures, integrity protection, fusion with existing robust controls, and combining preventive and emergent measures have been discussed. The implementation of recently applied ML, RL, and IoT strategies for energy management, conservation, and resilient operation is clarified in this paper. The proposed review highlights the advantages and drawbacks of the recent energy conservation strategies. Finally, the perspective solutions have been clarified to cope with the world direction for zero energy buildings.
A7: ORI-115 | B7: ScienceDirect | C7: 1 | D7: A comprehensive review of predictive control strategies in heating, ventilation, and air-conditioning (HVAC): Model-free VS model | E7: Xin, Xin; Zhang, Zhihao; Zhou, Yong; Liu, Yanfeng; Wang, Dengjia; Nan, Shuo | F7: 2024 | G7: JOUR | H7: Journal of Building Engineering | I7: 10.1016/j.jobe.2024.110013 | J7: Exclude | K7: Reinforcement learning is not the central review subject | L7: Historical eligibility assessment | M7: The historical title/abstract versus full-text split was not retained; reason reconstructed from the final scope and available record metadata. | N7: ScienceDirect_citations_1783952383784(1).ris | O7: Predictive control offers significant advantages in nonlinear control, high thermal inertia, and dynamic control. This article uses a Systematic Reviews and Meta-Analyses methodology to review 245 studies on predictive control in HVAC systems over the past 12 years, focusing on Model Predictive Control (MPC) and Model-Free Predictive Control (MFPC). In cooling systems, MPC is widely applied to energy efficiency management, continuous operation and maintenance, and overall system optimization in multi-zone residences. Its advantage is its ability to respond to system dynamics and precisely control key components such as cooling towers, condensers, evaporators, and pumps. Research focuses on simplifying models, reducing computational complexity, and enhancing real-time performance. In contrast, MFPC saves energy in equipment components and overall operation through intelligent valves, agent control programs, and other methods. Research focuses on developing new reinforcement learning algorithms to improve control efficiency and reliability. MPC research in heating systems focuses on hydraulic and thermal balance in central heating systems and expands to managing renewable energy hybrid systems. The research aims to dynamically adjust to meet user thermal comfort requirements while reducing energy consumption and improving efficiency. Key technologies include modeling techniques, distributed MPC, cross-regional integrated control, and efficient renewable energy integration strategies. MFPC precisely controls heating system water supply temperature, heat pump energy efficiency, and heating terminals through model-free algorithms like deep reinforcement learning and multivariable extremum seeking control. In integrated HVAC systems, MPC research focuses on managing multi-energy systems through hierarchical decomposition and multi-layer strategies, seamless renewable energy integration and optimization, and developing multi-objective optimization and decision support tools. MFPC research includes automatic grading strategies for integrated controllers, online optimization balancing methods, multi-agent methods, and developing intelligent model-free adaptive control strategies. However, MFPC integration in practical applications still needs strengthening. This review guides researchers in selecting the best predictive control mode for various HVAC system applications.
A8: ORI-134 | B8: IEEE Xplore | C8: 1 | D8: A Comprehensive Review of Reinforcement Learning Algorithms for Control Systems: Applications, Challenges, and Future Directions | E8: A. H. Abdul Hafez; U. Demircioglu; H. Bakir; R. Alzubi | F8: 2026 | G8: JOUR | H8: IEEE Access | I8: 10.1109/access.2026.3674539 | J8: Exclude | K8: Building control is not the central application domain | L8: Historical eligibility assessment | M8: The historical title/abstract versus full-text split was not retained; reason reconstructed from the final scope and available record metadata. | N8: ieee_final.ris | O8: Reinforcement Learning (RL) has emerged as a powerful paradigm for optimizing control systems by enabling autonomous decision-making in dynamic environments. This review provides a comprehensive analysis of RL algorithms applied to control systems, including robotics, industrial automation, and dynamic system control. A systematic review of more than 300 research papers was conducted to assess the advantages, limitations, and real-world applicability of various RL approaches. The study categorizes RL algorithms based on their applicability to discrete and continuous control problems and evaluates their effectiveness in comparison with traditional control techniques. Additionally, this review examines the integration of RL with conventional control strategies, highlighting the impact of such integration on adaptive learning, system efficiency, and decision optimization. Key challenges associated with RL in control applications, such as computational complexity, data efficiency, and generalization issues, are also discussed. By synthesizing existing literature and identifying research gaps, this review serves as a foundational resource for researchers and practitioners aiming to advance RL-driven control systems.
A9: ORI-140 | B9: IEEE Xplore | C9: 1 | D9: A Comprehensive Review of Topologies and Energy Management Methods for Hybrid Energy Storage Systems in Electric Vehicle Applications | E9: P. Ranjbaran; J. Ebrahimi; A. Bakhshai; P. K. Jain | F9: 2026 | G9: JOUR | H9: IEEE Transactions on Power Electronics | I9: 10.1109/tpel.2025.3625535 | J9: Exclude | K9: Reinforcement learning is not the central review subject | L9: Historical eligibility assessment | M9: The historical title/abstract versus full-text split was not retained; reason reconstructed from the final scope and available record metadata. | N9: ieee_final.ris | O9: Hybrid energy storage systems (HESSs), combining batteries and supercapacitors (SCs), have emerged as a promising solution to address the conflicting demands of high energy density, power density, and cycle life in electric vehicles (EVs). This article presents a comprehensive and up-to-date review of power converter topologies and energy management strategies (EMSs) for HESS integration in EVs. First, this article systematically classifies converter architectures into dual-stage, single-stage, and quasi-stage topologies to analyze their operational principles, control flexibility, efficiency, and suitability for modern EV applications. Detailed comparisons of semiactive, fully active, multi-input, and reconfigurable dual-stage converters, as well as advanced single-stage multisource inverter (MSI) configurations along with quasi-single-stage and quasi-dual-stage topologies, are provided. Next, the EMSs applicable to HESSs in EVs are reviewed and categorized into rule-based, optimization-based, machine learning (ML)-based, and hybrid methodologies. Recent advances in ML, particularly reinforcement learning algorithms, are critically examined for their potential in enabling adaptive, model-free energy management under complex and uncertain driving conditions. Comprehensive tables and comparative analyzes highlight the strengths, limitations, and validation methods of leading techniques. Finally, this article identifies key trends, technical challenges, and research gaps, and discusses future research directions to guide the codesign of converter topologies and intelligent EMSs for next-generation EVs.
A10: ORI-109 | B10: ScienceDirect | C10: 1 | D10: A critical review of field implementation of data-driven operation and maintenance technologies to reduce building energy use and GHG emissions | E10: Gunay, Burak; Markus, Andre; Parsaei, Arya; Darwazeh, Darwish; Bursill, Jayson; Pellerin, Luc | F10: 2025 | G10: JOUR | H10: Energy and Buildings | I10: 10.1016/j.enbuild.2025.116087 | J10: Exclude | K10: RL is one of six data-driven operation and maintenance application domains | L10: Full-text reassessment | M10: RL-specific evidence is not the organizing subject | N10: ScienceDirect_citations_1783952383784(1).ris | O10: Field implementation studies spanning six data-driven building operation and maintenance (DBOM) application domains (model-based predictive control (MPC), occupant-centric control (OCC), automated demand response (ADR), reinforcement learning control (RLC), fault detection and diagnostics (FDD), and virtual metering (VM)) were reviewed. The review aimed to make inter- and intra-application domain comparisons in terms of implementation processes and outcomes. The studies were classified by different levels of integration effort and sensing infrastructure complexity according to the quantity and kind of their inputs and outputs. An analysis is conducted on how energy-related success metrics (e.g., energy use, cost, demand) correlate with the integration effort and the complexity of the infrastructure. In general, MPC and ADR studies were found to require a higher level of integration effort than OCC studies; yet, OCC studies tend to require upgrades in the sensing infrastructure, unlike MPC and ADR studies. 95 % of those reporting post-implementation energy metrics achieved more than 10 % improvement in their energy-related objectives. The analysis results also highlight that a large fraction of the FDD and VM studies did not follow a measurement and verification procedure to quantify energy-related performance improvements upon field implementation. 90 % of the papers did not include feedback from building operators or occupants after the implementation.
A11: ORI-083 | B11: ScienceDirect | C11: 1 | D11: A critical review of safe reinforcement learning strategies in power and energy systems | E11: Bui, Van-Hai; Mohammadi, Sina; Das, Srijita; Hussain, Akhtar; Hollweg, Guilherme Vieira; Su, Wencong | F11: 2025 | G11: JOUR | H11: Engineering Applications of Artificial Intelligence | I11: 10.1016/j.engappai.2025.110091 | J11: Exclude | K11: Did not satisfy all centrality, publication-type, or scope criteria in the final eligibility assessment | L11: Historical eligibility assessment | M11: The historical title/abstract versus full-text split was not retained; reason reconstructed from the final scope and available record metadata. | N11: ScienceDirect_citations_1783952383784(1).ris | O11: The high penetration of distributed energy resources (DERs) in modern smart power systems introduces unforeseen uncertainties for the electricity sector, leading to increased complexity and difficulty in the operation and control of power systems. As a cutting-edge machine learning technology, deep reinforcement learning (DRL) has been widely implemented in recent years to handle the uncertainty in power systems. However, in critical infrastructures such as power systems, safety issues always receive top priority, while DRL may not always meet the safety requirements of power system operators. The concept of safe reinforcement learning (safe RL) is emerging as a potential solution to overcome the shortcomings of conventional DRL in the operation and control of power systems. This study provides a rigorous review of the latest research efforts focused on safe RL to derive power system control policies while accounting for the unique safety requirements of power grids. Furthermore, this study highlights various safe RL algorithms applied in diverse applications within the power and energy system sector, from single grid-connected power converters, residential smart homes, and buildings to large power distribution networks. For all methods outlined, a discussion on their bottlenecks, research challenges, and potential opportunities in the operation and control of power system applications is also presented. This review aims to support research in the area of safe RL algorithms, embracing smart power system operation with safety constraints amid high uncertainty from DERs.
A12: ORI-037 | B12: Web of Science | C12: 1 | D12: A Meta-Survey on Intelligent Energy-Efficient Buildings | E12: Islam, MB; Guerrieri, A; Gravina, R; Fortino, G | F12: 2024 | G12: JOUR | H12: BIG DATA AND COGNITIVE COMPUTING | I12: 10.3390/bdcc8080083 | J12: Exclude | K12: Reinforcement learning is not the central review subject | L12: Historical eligibility assessment | M12: The historical title/abstract versus full-text split was not retained; reason reconstructed from the final scope and available record metadata. | N12: wos_final.ris
A13: ORI-170 | B13: IEEE Xplore | C13: 1 | D13: A multi-faceted approach to electricity theft detection: Using community engagement, audit analytics, and machine learning algorithms | E13: C. A. Sibiya; K. A. Ogudo; E. Aladesanmi | F13: 2026 | G13: JOUR | H13: SAIEE Africa Research Journal | I13: 10.23919/saiee.2026.11484067 | J13: Exclude | K13: Not an eligible review/survey publication | L13: Historical eligibility assessment | M13: The historical title/abstract versus full-text split was not retained; reason reconstructed from the final scope and available record metadata. | N13: ieee_final.ris | O13: Electricity theft represents a significant source of non-technical losses (NTLs) in power distribution networks, leading to substantial financial deficits, grid instability, and safety concerns. This study introduces a machine learning-based methodology to detect and predict electricity theft by examining residential consumption patterns in Pietermaritzburg Municipality, South Africa. Utilising meter data from approximately 42,000 customers, of whom 21,935 made at least one electricity purchase over a five-year period (2019-2024), the research evaluates five machine learning techniques: decision trees, logistic regression, K-nearest neighbours, XGBoost, and random forests. The approach integrates survey data, audit outcomes, and audit evaluations for a holistic analysis. Results indicate that Random Forest outperforms other models, achieving the highest scores across accuracy (0.8), precision (0.75), recall (0.9), and F1-score (0.82) for detecting tampering. Survey findings reveal that 85.0% of respondents link theft to financial hardship, underscoring socio-economic influences. This study provides utilities with practical insights to reduce NTLs, enhance grid reliability, and foster sustainable energy management.
A14: ORI-077 | B14: ScienceDirect | C14: 1 | D14: A review of advanced ground source heat pump control: Artificial intelligence for autonomous and adaptive control | E14: Noye, Sarah; Mulero Martinez, Rubén; Carnieletto, Laura; De Carli, Michele; Castelruiz Aguirre, Amaia | F14: 2022 | G14: JOUR | H14: Renewable and Sustainable Energy Reviews | I14: 10.1016/j.rser.2021.111685 | J14: Exclude | K14: Reinforcement learning is not the central review subject | L14: Historical eligibility assessment | M14: The historical title/abstract versus full-text split was not retained; reason reconstructed from the final scope and available record metadata. | N14: ScienceDirect_citations_1783952383784(1).ris | O14: Geothermal energy has the potential to contribute significantly to the CO2 reduction targets as a renewable source for building heating and cooling but is yet under exploited, mostly due to its high initial investment cost. A lot of research is being carried out to optimise Ground Source Heat Pump (GSHP) systems’ design, but a good control strategy is also fundamental to achieve long-term performance and reduced payback time. GSHP control optimisation is a non-linear dynamic optimisation problem that is influenced by multiple parameters. It can thus not be fully optimised with traditional methods. Artificial Intelligence, and in particular Machine Learning, is suited for this type of optimisation as it can learn implicit relations between parameters and can address non-linearity. This paper reviews the challenges of GSHP control and the strategies for control optimisation found in the literature, from basic rule-based system to artificial neural network-based strategies. Two principal uses of Artificial Intelligence for ground source heat pump control are identified: building a predictive model of the system that reflects its real performances and optimising the control decision in real time. However, the examples found in the literature are limited and the need to further explore the benefits of Machine Learning is identified. The latest developments in the field are reviewed to explore their potential to further improve GSHP control. The challenges of the full implementation of such algorithms are also discussed.
A15: ORI-042 | B15: Web of Science | C15: 1 | D15: A review of building climate and plant controls, and a survey of industry perspectives | E15: Royapoor, M; Antony, A; Roskilly, T | F15: 2018 | G15: JOUR | H15: ENERGY AND BUILDINGS | I15: 10.1016/j.enbuild.2017.10.022 | J15: Exclude | K15: Reinforcement learning is not the central review subject | L15: Historical eligibility assessment | M15: The historical title/abstract versus full-text split was not retained; reason reconstructed from the final scope and available record metadata. | N15: wos_final.ris
A16: ORI-027 | B16: Web of Science; IEEE Xplore | C16: 2 | D16: A Review of Deep Reinforcement Learning for Smart Building Energy Management | E16: Yu, L; Qin, SQ; Zhang, M; Shen, C; Jiang, T; Guan, XH | F16: 2021 | G16: JOUR | H16: IEEE INTERNET OF THINGS JOURNAL | I16: 10.1109/jiot.2021.3078462 | J16: Include | K16: Eligible in the pre-existing coded corpus | L16: Full-text eligibility | M16: Final corpus | N16: wos_final.ris; ieee_final.ris
A17: ORI-034 | B17: Web of Science | C17: 1 | D17: A Review of Denial of Service Attack and Mitigation in the Smart Grid Using Reinforcement Learning | E17: Ortega-Fernandez, I; Liberati, F | F17: 2023 | G17: JOUR | H17: ENERGIES | I17: 10.3390/en16020635 | J17: Exclude | K17: Building control is not the central application domain | L17: Historical eligibility assessment | M17: The historical title/abstract versus full-text split was not retained; reason reconstructed from the final scope and available record metadata. | N17: wos_final.ris
A18: ORI-075 | B18: ScienceDirect | C18: 1 | D18: A review of reinforcement learning for autonomous building energy management | E18: Mason, Karl; Grijalva, Santiago | F18: 2019 | G18: JOUR | H18: Computers & Electrical Engineering | I18: 10.1016/j.compeleceng.2019.07.019 | J18: Include | K18: Eligible in the pre-existing coded corpus | L18: Full-text eligibility | M18: Final corpus | N18: ScienceDirect_citations_1783952383784(1).ris | O18: The area of building energy management has received a significant amount of interest in recent years. This area is concerned with combining advancements in sensor technologies, communications and advanced control algorithms to optimize energy utilization. Reinforcement learning is one of the most prominent machine learning algorithms used for control problems and has had many successful applications in the area of building energy management. This research gives a comprehensive review of the literature relating to the application of reinforcement learning to developing autonomous building energy management systems. Energy savings of greater than 20% are reported in the literature for more complex building energy management problems when implementing reinforcement learning. The main direction for future research and challenges in reinforcement learning are also outlined.
A19: ORI-022 | B19: Web of Science; ScienceDirect | C19: 2 | D19: A Review of Reinforcement Learning for Controlling Building Energy Systems From a Computer Science Perspective | E19: Weinberg, David; Wang, Qian; Timoudas, Thomas Ohlson; Fischione, Carlo | F19: 2023 | G19: JOUR | H19: Sustainable Cities and Society | I19: 10.1016/j.scs.2022.104351 | J19: Include | K19: Eligible in the pre-existing coded corpus | L19: Full-text eligibility | M19: Final corpus | N19: wos_final.ris; ScienceDirect_citations_1783952383784(1).ris | O19: Energy efficient control of energy systems in buildings is a widely recognized challenge due to the use of low temperature heating, renewable electricity sources, and the incorporation of thermal storage. Reinforcement Learning (RL) has been shown to be effective at minimizing the energy usage in buildings with maintained thermal comfort despite the high system complexity. However, RL has certain disadvantages that make it challenging to apply in engineering practices. In this review, we take a computer science approach to identifying three main categories of challenges of using RL for control of Building Energy Systems (BES). The three categories are the following: RL in single buildings, RL in building clusters, and multi-agent aspects. For each topic, we analyse the main challenges, and the state-of-the-art approaches to alleviate them. We also identify several future research directions on subjects such as sample efficiency, transfer learning, and the theoretical properties of RL in building energy systems. In conclusion, our review shows that the work on RL for BES control is still in its initial stages. Although significant progress has been made, more research is needed to realize the goal of RL-based control of BES at scale.
A20: ORI-093 | B20: ScienceDirect | C20: 1 | D20: A review of reinforcement learning methodologies for controlling occupant comfort in buildings | E20: Han, Mengjie; May, Ross; Zhang, Xingxing; Wang, Xinru; Pan, Song; Yan, Da; Jin, Yuan; Xu, Liguo | F20: 2019 | G20: JOUR | H20: Sustainable Cities and Society | I20: 10.1016/j.scs.2019.101748 | J20: Exclude | K20: Duplicate/overlapping review | L20: Historical eligibility assessment | M20: Identified during revision; this record had been mislabelled as the coded Han corpus member, and the coded member is Han et al. (2021), ORI-059. Excluded under the Independence criterion as a companion report of the same review programme. Han et al. (2021), the coded corpus member, states in its own Section 2.2 that "an agent that tried to learn the optimal control strategy only to satisfy occupant comfort and did not include dynamic interactions with the environment was excluded from this analysis. See a relevant review work [24] that examined the RL control for occupant comfort for more articles that we exclude here", where its reference [24] is this record. The two reviews therefore partition one evidence base between them. Because the unit of analysis in this tertiary review is the review, counting both companion reports would double-weight one team's editorial choices in every research-question denominator. The later report, whose scope is RL within building control with occupant behaviour inside the MDP, is retained. | N20: ScienceDirect_citations_1783952383784(1).ris | O20: Classical building control systems are becoming vulnerable with increasing complexities in contemporary built environments and energy systems. Due to this, the reinforcement learning (RL) method is becoming more distinctive and applicable in control networks for buildings. This paper, therefore, conducts a comprehensive review of RL techniques applied in control systems for occupant comfort in indoor built environments. The empirical applications of RL-based control systems are presented, depending on comfort objectives (thermal comfort, indoor air quality, and lighting) along with other objectives which invariably includes energy consumption. The class of RL algorithms and implementation details regarding how the value functions have been represented and how the policies are improved are also illustrated. This paper shows there are limited works for which RL has been explored for controlling occupant comfort, especially in indoor air quality and lighting. Relatively few of the reviewed works incorporate occupancy patterns and/or occupant feedback into the control loop. Moreover, this paper identifies a gap with regard to the performance of implementing cooperative multi-agent RL (MARL). Based on our findings, current challenges and further opportunities are discussed. We expect to clarify the feasible theory and functions of RL for building control systems, which would promote their wider-spread application in built environments.
A21: ORI-144 | B21: IEEE Xplore | C21: 1 | D21: A Review of Safe Reinforcement Learning Methods for Modern Power Systems | E21: T. Su; T. Wu; J. Zhao; A. Scaglione; L. Xie | F21: 2025 | G21: JOUR | H21: Proceedings of the IEEE | I21: 10.1109/jproc.2025.3584656 | J21: Exclude | K21: Building control is not the central application domain | L21: Historical eligibility assessment | M21: The historical title/abstract versus full-text split was not retained; reason reconstructed from the final scope and available record metadata. | N21: ieee_final.ris | O21: Given the availability of more comprehensive measurement data in modern power systems, reinforcement learning (RL) has gained significant interest in operation and control. Conventional RL relies on trial-and-error interactions with the environment and reward feedback, which often leads to exploring unsafe operating regions and executing unsafe actions, especially when deployed in real-world power systems. To address these challenges, safe RL has been proposed to optimize operational objectives while ensuring safety constraints are met, keeping actions and states within safe regions throughout both training and deployment. Rather than relying solely on manually designed penalty terms for unsafe actions, as is common in conventional RL, safe RL methods reviewed here primarily leverage advanced and proactive mechanisms. These include techniques such as Lagrangian relaxation, safety layers, and theoretical guarantees like Lyapunov functions to rigorously enforce safety boundaries. This article provides a comprehensive review of safe RL methods and their applications across various power system operations and control domains, including security control, real-time operation, operational planning, and emerging areas. It summarizes existing safe RL techniques, evaluates their performance, analyzes suitable deployment scenarios, and examines algorithm benchmarks and application environments. This article also highlights real-world implementation cases and identifies critical challenges such as scalability in large-scale systems and robustness under uncertainty, providing potential solutions and outlining future directions to advance the reliable integration and deployment of safe RL in modern power systems.
A22: ORI-138 | B22: IEEE Xplore | C22: 1 | D22: A Review on Optimal Energy Management of Multimicrogrid System Considering Uncertainties | E22: G. Ma; J. Li; X. -P. Zhang | F22: 2022 | G22: JOUR | H22: IEEE Access | I22: 10.1109/access.2022.3192638 | J22: Exclude | K22: Reinforcement learning is not the central review subject | L22: Historical eligibility assessment | M22: The historical title/abstract versus full-text split was not retained; reason reconstructed from the final scope and available record metadata. | N22: ieee_final.ris | O22: Microgrid (MG) is one of the most effective solution to integrate distributed renewable energy into power system. However, modern MG has several technical challenges such as migration to multi vector energy system, increasing renewable energy penetration, and the uncertainties that arise from the large-scale incorporation of renewable energy. Recent development of multi-microgrid (MMG) could potentially mitigate these challenges. MMG has obvious advantages in improving the system stability, reliability, economy, and energy efficiency of power grid operation through autonomous management and coordinated control among networked MGs. In the meantime, uncertainties from many elements and operators in the MMG system also pose huge challenges in modeling. This paper will present and review typical architecture of MMG, including physical layer, information layer and application layer. Moreover, this paper will critically review and analyze challenges in uncertainty modelling and solution in MMGs. Finally, the paper will also discuss future research areas and development trends of MMG.
A23: ORI-038 | B23: Web of Science | C23: 1 | D23: A state-of-the-art review and bibliometric analysis on the sizing optimization of off-grid hybrid renewable energy systems | E23: He, Y; Guo, S; Dong, PX; Zhang, Y; Huang, J; Zhou, JX | F23: 2023 | G23: JOUR | H23: RENEWABLE & SUSTAINABLE ENERGY REVIEWS | I23: 10.1016/j.rser.2023.113476 | J23: Exclude | K23: Reinforcement learning is not the central review subject | L23: Historical eligibility assessment | M23: The historical title/abstract versus full-text split was not retained; reason reconstructed from the final scope and available record metadata. | N23: wos_final.ris
A24: ORI-032 | B24: Web of Science | C24: 1 | D24: A survey for deep reinforcement learning in markovian cyber-physical systems: Common problems and solutions | E24: Rupprecht, T; Wang, YZ | F24: 2022 | G24: JOUR | H24: NEURAL NETWORKS | I24: 10.1016/j.neunet.2022.05.013 | J24: Exclude | K24: Building control is not the central application domain | L24: Historical eligibility assessment | M24: The historical title/abstract versus full-text split was not retained; reason reconstructed from the final scope and available record metadata. | N24: wos_final.ris
A25: ORI-031 | B25: Web of Science | C25: 1 | D25: A Survey of Intelligent End-to-End Networking Solutions: Integrating Graph Neural Networks and Deep Reinforcement Learning Approaches | E25: Tam, P; Ros, S; Song, I; Kang, S; Kim, S | F25: 2024 | G25: JOUR | H25: ELECTRONICS | I25: 10.3390/electronics13050994 | J25: Exclude | K25: Building control is not the central application domain | L25: Historical eligibility assessment | M25: The historical title/abstract versus full-text split was not retained; reason reconstructed from the final scope and available record metadata. | N25: wos_final.ris
A26: ORI-149 | B26: IEEE Xplore | C26: 1 | D26: A Survey of Multi-Agent Reinforcement Learning for Cooperative Control in Multi-AUV Systems | E26: A. Wibisono; H. -K. Song; B. M. Lee | F26: 2025 | G26: JOUR | H26: IEEE Access | I26: 10.1109/access.2025.3609457 | J26: Exclude | K26: Building control is not the central application domain | L26: Historical eligibility assessment | M26: The historical title/abstract versus full-text split was not retained; reason reconstructed from the final scope and available record metadata. | N26: ieee_final.ris | O26: The increasing demand for adaptive and autonomous smart ocean systems has accelerated the deployment of Autonomous Underwater Vehicles (AUVs) in various complex underwater missions, including collaborative navigation, target tracking, data collection, and energy management. To address the inherent challenges of the underwater environment, such as the limitations of acoustic communication, unpredictable environmental dynamics, and partial observability, Multi-Agent Reinforcement Learning (MARL) with the Centralized Training with Decentralized Execution (CTDE) paradigm has emerged as a promising solution. This paper presents a focused survey on MARL algorithms and their applications in multi-AUV systems. We classify the algorithms into value-based approaches (e.g., VDN and QMIX), policy-based approaches (e.g., Multi-Agent Deep Deterministic Policy Gradient (MADDPG) and Multi-Agent Proximal Policy Optimization (MAPPO)), and hybrid approaches that support explicit communication (e.g., CommNet, DIAL, and ROMA). We further review several relevant simulation environments, such as PettingZoo, UWSim, and Gazebo, along with underwater acoustic channel modeling and key performance metrics used for system evaluation. Complementing the survey study, we present representative experiments in data collection and energy efficiency scenarios using MADDPG and MAPPO algorithms. The results include comparative analyses of average reward, overflow, Flight eXceedance (FX), and energy consumption, accompanied by trajectory visualizations in a grid-based simulation environment. Finally, we provide a synthesis of future research directions, including the integration of Meta-Reinforcement Learning (Meta-RL), graph-based role allocation, and 3D physics-based simulator training, to strengthen the adoption of MARL in autonomous ocean systems. This survey is expected to serve as a reference point for further research in developing AUVs that are smarter, more collaborative, and resilient to extreme conditions.
A27: ORI-159 | B27: IEEE Xplore | C27: 1 | D27: A survey on algorithms for intelligent computing and smart city applications | E27: Z. Tong; F. Ye; M. Yan; H. Liu; S. Basodi | F27: 2021 | G27: JOUR | H27: Big Data Mining and Analytics | I27: 10.26599/bdma.2020.9020029 | J27: Exclude | K27: Reinforcement learning is not the central review subject | L27: Historical eligibility assessment | M27: The historical title/abstract versus full-text split was not retained; reason reconstructed from the final scope and available record metadata. | N27: ieee_final.ris | O27: With the rapid development of human society, the urbanization of the world's population is also progressing rapidly. Urbanization has brought many challenges and problems to the development of cities. For example, theurban population is under excessive pressure, various natural resources and energy are increasingly scarce, and environmental pollution is increasing, etc. However, the original urban model has to be changed to enable peopleto live in greener and more sustainable cities, thus providing them with a more convenient and comfortable living environment. The new urban framework, the smart city, provides excellent opportunities to meet these challenges, while solving urban problems at the same time. At this stage, many countries are actively responding to calls for smart city development plans. This paper investigates the current stage of the smart city. First, it introduces the background of smart city development and gives a brief definition of the concept of the smart city. Second, it describes the framework of a smart city in accordance with the given definition. Finally, various intelligent algorithms to make cities smarter, along with specific examples, are discussed and analyzed.
A28: ORI-029 | B28: Web of Science | C28: 1 | D28: A Sustainability Evaluation of Buildings: A Review on Sustainability Factors to Move towards a Greener City Environment | E28: Park, S; Cho, KH; Choi, MI | F28: 2024 | G28: JOUR | H28: BUILDINGS | I28: 10.3390/buildings14020446 | J28: Exclude | K28: Reinforcement learning is not the central review subject | L28: Historical eligibility assessment | M28: The historical title/abstract versus full-text split was not retained; reason reconstructed from the final scope and available record metadata. | N28: wos_final.ris
A29: ORI-119 | B29: ScienceDirect | C29: 1 | D29: A systematic review of building energy performance forecasting approaches | E29: Yang, Yizhou; Duan, Qiuhua; Samadi, Forooza | F29: 2025 | G29: JOUR | H29: Renewable and Sustainable Energy Reviews | I29: 10.1016/j.rser.2025.116061 | J29: Exclude | K29: Reinforcement learning is not the central review subject | L29: Historical eligibility assessment | M29: The historical title/abstract versus full-text split was not retained; reason reconstructed from the final scope and available record metadata. | N29: ScienceDirect_citations_1783952383784(1).ris | O29: Building energy performance forecasting (BEPF) is an active area of research with the potential to improve the efficiency of building energy management systems, support global sustainability goals, and mitigate climate change impacts. This systematic review examines three main prediction methods: model-driven, data-driven, and hybrid-driven, each with different principles, basics, advantages, disadvantages, practical applications, challenges, and limitations in addressing the complexities of building energy performance. The review focuses on key influencing factors, including building features, climatic conditions, and occupant behavior, while identifying critical research gaps in current methodologies. Through a bibliometric analysis of 95 relevant publications from 2019 to 2024, this review provides a quantitative overview of research progress and emerging trends. Findings indicate that although BEPF techniques have evolved rapidly, most studies continue to overlook the variability and complexity of occupant behavior, a factor with significantly affects forecast accuracy. To address this, we propose a modular AI-integrated forecasting framework that leverages the strengths of existing approaches, integrates real-time IoT data, and incorporate advanced artificial intelligence techniques, such as generative Artificial Intelligence, reinforcement learning, and Large Language Models (LLMs). A decision-making framework is also introduced to guide method selection based on specific building characteristics, data availability, desired accuracy, and operational goals, offering practical guidance for engineering and policy applications. Additionally, future research should extend beyond individual building dynamics to include a wider range of community-level determinants, such as policy frameworks, economic factors, and social determinants of health considerations (SDOH), aiming for a more comprehensive understanding of building energy consumption patterns. This review not only synthesizes current knowledge but also lays the foundation for future innovations in BEPF. We advocate for moving towards an AI-enhanced, adaptive forecasting model that can integrate different driven methods, capture the variability and unpredictability of occupant behavior, and improve the accuracy and reliability of energy forecasts.
A30: ORI-050 | B30: Web of Science | C30: 1 | D30: A systematic review of machine learning techniques related to local energy communities | E30: Hernandez-Matheus, A; Löschenbrand, M; Berg, K; Fuchs, I; Aragüés-Peñalba, M; Bullich-Massagué, E; Sumper, A | F30: 2022 | G30: JOUR | H30: RENEWABLE & SUSTAINABLE ENERGY REVIEWS | I30: 10.1016/j.rser.2022.112651 | J30: Exclude | K30: Reinforcement learning is not the central review subject | L30: Historical eligibility assessment | M30: The historical title/abstract versus full-text split was not retained; reason reconstructed from the final scope and available record metadata. | N30: wos_final.ris
A31: ORI-099 | B31: ScienceDirect | C31: 1 | D31: A systematic review of predictive, optimization, and smart control strategies for hydrogen-based building heating systems | E31: Kaabinejadian, Amirreza; Pozarlik, Artur; Acar, Canan | F31: 2025 | G31: JOUR | H31: Applied Energy | I31: 10.1016/j.apenergy.2024.124994 | J31: Exclude | K31: Reinforcement learning is not the central review subject | L31: Historical eligibility assessment | M31: The historical title/abstract versus full-text split was not retained; reason reconstructed from the final scope and available record metadata. | N31: ScienceDirect_citations_1783952383784(1).ris | O31: The use of energy in the built environment contributes to over one-third of the world's carbon emissions. To reduce that effect, two primary solutions can be adopted, i.e. (i) renovation of old buildings and (ii) increasing the renewable energy penetration. This review paper focuses on the latter. Renewable energy sources typically have an intermittent nature. In other words, it is not guaranteed that these sources can be harnessed on demand. Thus, complement solutions should be considered to use renewable energy sources efficiently. Hydrogen is recognized as a potential solution. It can be used to store excess energy or be directly exploited to generate thermal energy. Throughout this review, various research papers focusing on hydrogen-based heating systems were reviewed, analyzed, and classified from different perspectives. Subsequently, articles related to machine learning models, optimization algorithms, and smart control systems, along with their applications in building energy management were reviewed to outline their potential contributions to reducing energy use, lowering carbon emissions, and improving thermal comfort for occupants. Furthermore, research gaps in the use of these smart strategies in residential hydrogen heating systems were thoroughly identified and discussed. The presented findings indicate that the semi-decentralized hydrogen-based heating systems hold significant potential. First, these systems can control the thermal demand of neighboring homes through local substations; second, they can reduce reliance on power and gas grids. Furthermore, the model predictive control and reinforcement learning approaches outperform other control systems ensuring energy comfort and cost-effective energy bills for residential buildings.
A32: ORI-069 | B32: ScienceDirect | C32: 1 | D32: A systematic review of reinforcement learning application in building energy-related occupant behavior simulation | E32: Yu, Hao; Tam, Vivian W.Y.; Xu, Xiaoxiao | F32: 2024 | G32: JOUR | H32: Energy and Buildings | I32: 10.1016/j.enbuild.2024.114189 | J32: Exclude | K32: Did not satisfy all centrality, publication-type, or scope criteria in the final eligibility assessment | L32: Historical eligibility assessment | M32: The historical title/abstract versus full-text split was not retained; reason reconstructed from the final scope and available record metadata. | N32: ScienceDirect_citations_1783952383784(1).ris | O32: The building and construction industry has consistently been a major contributor to energy consumption and carbon emissions. With stochastic interactions between occupants and building energy systems, the operational phase has emerged as the most energy-intensive stage throughout a building’s lifecycle. In the face of challenges posed by traditional control strategies, reinforcement learning distinguishes itself with its capacity to effectively characterize dynamic occupant-building interactions and iteratively generate optimal control strategies through self-learning. However, the valuable knowledge about reinforcement learning applications scattered in the growing body of occupant behavior research has not been systematically integrated. As a result, this research innovatively combines bibliometrics and content analysis to provide a systematic review aiming to answer how reinforcement learning can be effectively adopted in occupant-centric building energy management based on existing knowledge. The state-of-the-art developments in related domains and a taxonomy of reinforcement learning are introduced based on the dissection of core concepts in occupant behavior and reinforcement learning. Subsequently, a novel framework for the complete application process of reinforcement learning in the domain of occupant energy-related behavior is originally proposed, providing potential researchers with rich existing knowledge and guidance. Moreover, future breakthroughs in framework design, data collection, agent training, and deployment are inspired through systematically concluded future directions, thus laying a solid foundation to better satisfy occupant comfort with optimal energy efficiency.
A33: ORI-066 | B33: ScienceDirect | C33: 1 | D33: A systematic review of reinforcement learning in Building-Integrated Photovoltaic (BIPV) optimization | E33: Li, Jiaqi; Xie, Hongbin; Zhang, Jingyuan; Li, Lianxin; Song, Ge; Fu, Hongdi; Chen, Panxi; Liu, Chenyang; Zhang, Liyu; Shi, Zhuoran; Yu, Qing; Song, Xuan; Zhang, Haoran | F33: 2025 | G33: JOUR | H33: Advances in Applied Energy | I33: 10.1016/j.adapen.2025.100239 | J33: Include | K33: Eligible journal review centered on RL-based operational scheduling and energy management of BIPV systems, rather than PV sizing or placement | L33: Full-text eligibility | M33: Final corpus | N33: ScienceDirect_citations_1783952383784(1).ris | O33: Building-Integrated Photovoltaic (BIPV), as an emerging clean energy solution, plays a crucial role in energy saving, emission reduction, and grid load regulation. However, due to the uncertainty of dynamic environments and the complexity of multiple sensitive parameters, traditional scheduling methods fail to achieve optimal results. Considering that reinforcement learning, as an advanced research approach, demonstrates great potential in decision-making for high-dimensional problems and stability in dynamic environments, integrating reinforcement learning with BIPV is a feasible solution to address scheduling challenges in BIPV systems. However, there is still a lack of comprehensive analysis and systematic understanding of reinforcement learning applications in the BIPV field, which, to some extent, limits its further development in the BIPV domain. To this end, this review conducts an in-depth analysis of the effectiveness of reinforcement learning in BIPV applications from the perspective of the system construction life cycle. By considering the algorithm modeling life cycle of reinforcement learning, it comprehensively examines the potential issues in its application to BIPV, highlighting the challenges faced by existing research and future applications. Additionally, this paper integrates cutting-edge reinforcement learning knowledge, summarizes and categorizes its potential applications in BIPV, providing reference guidance for future research directions. Through this systematic review of reinforcement learning applications in the BIPV field, this study aims to offer valuable insights for subsequent research.
A34: ORI-028 | B34: Web of Science | C34: 1 | D34: A systematic survey on demand response management schemes for electric vehicles | E34: Kakkar, R; Agrawal, S; Tanwar, S | F34: 2024 | G34: JOUR | H34: RENEWABLE & SUSTAINABLE ENERGY REVIEWS | I34: 10.1016/j.rser.2024.114748 | J34: Exclude | K34: Reinforcement learning is not the central review subject | L34: Historical eligibility assessment | M34: The historical title/abstract versus full-text split was not retained; reason reconstructed from the final scope and available record metadata. | N34: wos_final.ris
A35: ORI-082 | B35: ScienceDirect | C35: 1 | D35: Advanced controls on energy reliability, flexibility and occupant-centric control for smart and energy-efficient buildings | E35: Liu, Zhengxuan; Zhang, Xiang; Sun, Ying; Zhou, Yuekuan | F35: 2023 | G35: JOUR | H35: Energy and Buildings | I35: 10.1016/j.enbuild.2023.113436 | J35: Exclude | K35: Not an eligible review/survey publication | L35: Historical eligibility assessment | M35: The historical title/abstract versus full-text split was not retained; reason reconstructed from the final scope and available record metadata. | N35: ScienceDirect_citations_1783952383784(1).ris | O35: Advanced controls have attracted increasing interests due to the high requirement on smart and energy-efficient (SEE) buildings and decarbonization in the building industry with optimal tradeoff strategies between energy consumption and thermal comfort of built environment. However, a state-of-the-art review is lacking on advanced controls for SEE buildings, especially considering advanced building energy systems, machine learning based advanced controls, and advanced occupant-centric controls (OCC). This study presents a comprehensive review on the latest advancement of advanced controls for SEE buildings, which covers recent research on data collection through smart metering and sensors, big data and building automation, energy digitization, and building energy simulation. Machine learning based advanced controls are comprehensively reviewed, including supervised, unsupervised and reinforcement learning, together with their roles and underlying mechanisms. In addition, advanced controls for energy security, reliability, robustness, flexibility, and resilience are further reviewed for energy-efficient and low-carbon buildings, with respect to fault detection and diagnosis, fire alarming and building energy safety, and climate change adaptation. Moreover, this study explores the advanced OCC systems and their applications in SEE buildings. Last but not the least, this study emphasizes the challenges and future prospects of the trade-off between complexity and predictive/control performance, AI-based controllers and climate change adaptation, OCC in thermal comfort and energy saving for the SEE buildings. This study offers valuable insights into the latest research progress concerning the underlying mechanisms, algorithms and applications of advanced controls for SEE buildings, paving the path for sustainable and low-carbon transition in building sectors.
A36: ORI-023 | B36: Web of Science; ScienceDirect | C36: 2 | D36: Advances of machine learning in multi-energy district communities‒ mechanisms, applications and perspectives | E36: Zhou, Yuekuan | F36: 2022 | G36: JOUR | H36: Energy and AI | I36: 10.1016/j.egyai.2022.100187 | J36: Exclude | K36: Not an eligible review/survey publication | L36: Historical eligibility assessment | M36: The historical title/abstract versus full-text split was not retained; reason reconstructed from the final scope and available record metadata. | N36: wos_final.ris; ScienceDirect_citations_1783952383784(1).ris | O36: Energy paradigm transition towards the carbon neutrality requires combined and continuous efforts in cleaner power production, advanced energy storages, flexible district energy demands and energy management strategies. Applications of cutting-edge machine learning techniques can improve the system reliability with advanced fault detection and diagnosis (FDD, automation with agent-based reinforcement learning, flexibility with model predictive controls, and so on. In this study, a comprehensive review on artificial intelligence applications in carbon-neutral district community, has been conducted, from perspectives of energy supply, energy storage, district demands and energy management. Classifications and underlying mechanisms on ML techniques have been demonstrated, including supervised, unsupervised, reinforcement and deep learning. Afterwards, practical applications of ML have been reviewed, in respect to renewable energy supply, hybrid energy storages, district energy demand and advanced energy management. Results indicate that, supervised learning was mainly applied in classification and regression, and unsupervised learning was mainly applied in clustering. The reinforcement learning is mainly applied in on-line optimal scheduling for building energy management. With respect to clean energy supply, ML in solar and wind energy systems mainly include solar irradiance forecasting, wind resource forecasting, PV power prediction, maximum power point tracking (MPPT) for smart control, fault detection and diagnosis. ML in fuel cells mainly includes performance prediction, material selection, combination and so on. Furthermore, in respect to hybrid energy storages, ML in electrochemical battery includes dynamic thermal/electrical behavior, battery sizing and optimization, state-of-charge prediction, battery lifetime estimation, fault detection and diagnosis analysis. ML in sensible energy storages mainly include load prediction and storage capacity sizing, dynamic scheduling for cost saving, thermal stratification analysis and dynamic performance prediction. Advances in energy management with ML mainly include dispatch on stochastic and intermittent renewable power, microgrid adaptive control, smart energy trading with controls and decision-marking. Research tendency over the recent past several years indicates that, critical areas for low-carbon energy systems transit from the only renewable systems (59.4% in 2016) towards both renewable energy supply and energy storages (35.1% and 34.1%, respectively), such as battery, capacitors/supercapacitors, sensible/latent heat storages, compressed air storage and hydrogen storage. This study can provide a holistic overview and in-depth thinking on artificial intelligence in the carbon-neutral district transition.
A37: ORI-152 | B37: IEEE Xplore | C37: 1 | D37: Advancing Power System Services With Privacy-Preserving Federated Learning Techniques: A Review | E37: R. Zheng; A. Sumper; M. Aragüés-Peñalba; S. Galceran-Arellano | F37: 2024 | G37: JOUR | H37: IEEE Access | I37: 10.1109/access.2024.3407121 | J37: Exclude | K37: Reinforcement learning is not the central review subject | L37: Historical eligibility assessment | M37: The historical title/abstract versus full-text split was not retained; reason reconstructed from the final scope and available record metadata. | N37: ieee_final.ris | O37: Digitalization has enabled the potential for artificial intelligence techniques to lead the power system to a sustainable transition by extracting the data generated by widely deployed edge devices, including advanced sensing and metering. Due to the increasing concerns about data privacy, federated learning has attracted much attention and is emerging as an innovative application for machine learning solutions in the power and energy sector. This paper presents a holistic analysis of federated learning applications in the energy sector, ranging from applications in generation, microgrids, and distribution systems to the energy market and cyber security. The following federated learning-based services for energy sectors are analyzed: non-intrusive load monitoring, fault detection, energy theft detection, demand forecasting, generation forecasting, energy management systems, voltage control, anomaly detection, and energy trading. The identification and classification of the data-driven methods are conducted in collaboration with federated learning implemented in these services. Furthermore, the interrelation is mapped between the categories of machine learning, data-driven techniques, the application domain, and application services. Finally, the future opportunities and challenges of applying federated learning in the energy sector will be discussed.
A38: ORI-169 | B38: IEEE Xplore | C38: 1 | D38: Advancing State of Charge Management in Electric Vehicles With Machine Learning: A Technological Review | E38: A. Mousaei; Y. Naderi; I. S. Bayram | F38: 2024 | G38: JOUR | H38: IEEE Access | I38: 10.1109/access.2024.3378527 | J38: Exclude | K38: Reinforcement learning is not the central review subject | L38: Historical eligibility assessment | M38: The historical title/abstract versus full-text split was not retained; reason reconstructed from the final scope and available record metadata. | N38: ieee_final.ris | O38: As the share of electric vehicles increases, electric vehicles are exposed to broader of driving conditions (e.g., extreme weather), which reduce the performance and driving ranges of electric vehicles below their nameplate rating. To ensure customer confidence and support steady growth in electric vehicle adoption rates, accurate estimation of battery state of charge and maintaining battery state of health through optimal charge/discharge decisions are critical. Recently, vehicle manufacturers have begun to employ machine learning techniques to improve state-of-charge management to better inform drivers about both the short-term (state of charge) and long-term (state of health) performance of their vehicles. This comprehensive review article explores the intersection of machine learning and state of charge management in electric vehicles. Recognizing the critical importance of the state of charge in optimizing electric vehicle performance, the article starts by evaluating traditional state of charge estimation methods. Subsequently, it delves into the transformative impact of machine learning techniques and associated algorithms on state of charge management. Through the lens of various case studies, this article demonstrates how machine learning-based state of charge estimation empowers electric vehicles to make informed and dynamic energy usage decisions, enhancing efficiency and extending battery life. The challenges of data availability, model interpretability, and real-time processing constraints are acknowledged as impediments to the widespread adoption of machine learning techniques. Despite these challenges, the future outlook for machine learning in the state of charge management appears promising, with emerging trends such as deep learning and reinforcement learning poised to refine the state of charge estimation accuracy. Moreover, this study sheds light on the transformative potential of machine learning in enhancing the state of charge management efficiency and effectiveness for electric vehicles, offering critical insights. Machine learning emerges as a game-changing force in state of charge management for electric vehicles, paving the way for intelligent and adaptive vehicles that are both environmentally friendly and efficient. This evolving field invites further research and development, making it a vital and exciting area within the automotive industry.
A39: ORI-054 | B39: Web of Science | C39: 1 | D39: AI Applications to Enhance Resilience in Power Systems and Microgrids-A Review | E39: Zahraoui, Y; Korotko, T; Rosin, A; Mekhilef, S; Seyedmahmoudian, M; Stojcevski, A; Alhamrouni, I | F39: 2024 | G39: JOUR | H39: SUSTAINABILITY | I39: 10.3390/su16124959 | J39: Exclude | K39: Reinforcement learning is not the central review subject | L39: Historical eligibility assessment | M39: The historical title/abstract versus full-text split was not retained; reason reconstructed from the final scope and available record metadata. | N39: wos_final.ris
A40: ORI-033 | B40: Web of Science | C40: 1 | D40: AI-Empowered Methods for Smart Energy Consumption: A Review of Load Forecasting, Anomaly Detection and Demand Response | E40: Wang, XL; Wang, H; Bhandari, B; Cheng, LM | F40: 2024 | G40: JOUR | H40: INTERNATIONAL JOURNAL OF PRECISION ENGINEERING AND MANUFACTURING-GREEN TECHNOLOGY | I40: 10.1007/s40684-023-00537-0 | J40: Exclude | K40: Reinforcement learning is not the central review subject | L40: Historical eligibility assessment | M40: The historical title/abstract versus full-text split was not retained; reason reconstructed from the final scope and available record metadata. | N40: wos_final.ris
A41: ORI-151 | B41: IEEE Xplore | C41: 1 | D41: AI-Enabled Energy Management for Sustainable Smart Greenhouses: An Integrated Review | E41: S. Ranjan Biswal; T. Roy Choudhury; B. Panda; S. Mishra | F41: 2026 | G41: JOUR | H41: IEEE Access | I41: 10.1109/access.2026.3651685 | J41: Exclude | K41: Reinforcement learning is not the central review subject | L41: Historical eligibility assessment | M41: The historical title/abstract versus full-text split was not retained; reason reconstructed from the final scope and available record metadata. | N41: ieee_final.ris | O41: Greenhouse based Controlled Environment Agriculture enables year round crop production. Maintaining a specific microclimate requires a significant amount of energy for controlling the atmosphere under the environment. Rising electricity prices, irregular solar energy generation, and specific microclimate requirements create challenges in operations and the economic viability of the system, thus demanding smart energy optimization. This creates a technical need for advanced Demand Side Management (DSM) techniques capable of aligning load operation with forecasted demand, renewable output, and market signals. Traditional strategies such as fixed rules, time slot scheduling, or heuristic controls offer limited adaptability, lack robustness under uncertainty, and do not generalize across climate zones or crop requirements. Recent developments introduce hybrid AI driven DSM frameworks that combine forecasting, optimization, and autonomous control using approaches such as Deep Learning (DL) based predictors, Model Predictive Control schedulers, and exploration Reinforcement Learning policies to enhance renewable utilisation, reduce cost, and maintain microclimate stability. This review systematically analyzes these methodological shifts, comparing forecasting, scheduling, and control approaches in terms of predictive performance, computational overhead, and deployment feasibility. Recurring challenges including limited transferability across climates, insufficient reporting of techno economic outcomes, and weak validation against biological risk constraints are examined alongside potential solutions such as uncertainty quantification, domain adaptation, and assessment of reliability. The outlines research priorities standardised evaluation directions to support robust, scalable, and commercially relevant DSM adoption in smart greenhouse environments.
A42: ORI-058 | B42: ScienceDirect | C42: 1 | D42: An overview of machine learning applications for smart buildings | E42: Alanne, Kari; Sierla, Seppo | F42: 2022 | G42: JOUR | H42: Sustainable Cities and Society | I42: 10.1016/j.scs.2021.103445 | J42: Exclude | K42: Reinforcement learning is not the central review subject | L42: Historical eligibility assessment | M42: Identified during revision. This record was previously mislabelled as the coded Sierla corpus member; the coded member is Sierla et al. (2022), Energies 15(10):3526, which appears only in the sensitivity export (SENS-036). The present record is a broad machine-learning overview in which RL is one method among several. | N42: ScienceDirect_citations_1783952383784(1).ris
A43: ORI-026 | B43: Web of Science | C43: 1 | D43: An overview of reinforcement learning-based approaches for smart home energy management systems with energy storages | E43: Pinthurat, W; Surinkaew, T; Hredzak, B | F43: 2024 | G43: JOUR | H43: RENEWABLE & SUSTAINABLE ENERGY REVIEWS | I43: 10.1016/j.rser.2024.114648 | J43: Include | K43: Eligible in the pre-existing coded corpus | L43: Full-text eligibility | M43: Final corpus | N43: wos_final.ris
A44: ORI-104 | B44: ScienceDirect | C44: 1 | D44: Application and progress of artificial intelligence technology in the field of distribution network voltage Control：A review | E44: Zhang, Xiao; Wu, Zhi; Sun, Qirun; Gu, Wei; Zheng, Shu; Zhao, Jingtao | F44: 2024 | G44: JOUR | H44: Renewable and Sustainable Energy Reviews | I44: 10.1016/j.rser.2024.114282 | J44: Exclude | K44: Reinforcement learning is not the central review subject | L44: Historical eligibility assessment | M44: The historical title/abstract versus full-text split was not retained; reason reconstructed from the final scope and available record metadata. | N44: ScienceDirect_citations_1783952383784(1).ris | O44: The increasing integration of distributed energy resources has led to heightened complexity in distribution network models, posing challenges of uncertainty and volatility to the operation and control of distribution networks. Simultaneously, the widespread deployment of metering and sensing devices has furnished data-driven approaches with copious data sources. As a potent tool for data mining, artificial intelligence (AI) algorithms have the capacity to harness extensive datasets, thus furnishing comprehensive energy services for distribution grids. This paper provides a comprehensive exposition of AI techniques applied in the realm of distribution network voltage control (DNVC). Initially, a brief overview is provided for the four voltage control frameworks and the data calibration of DNVC, serving as the foundation for various voltage control algorithms. Subsequently, in ascending order of algorithmic advancement, the application of improved heuristic algorithms, deep learning (DL) algorithms structured around artificial neural networks (ANNs), and deep reinforcement learning (DRL) algorithms in the DNVC domain are sequentially introduced, and the relationships among the three AI technologies in framework, control principles, and performance are systematically analyzed. Additionally, attention is directed toward the algorithmic progress made in addressing specific challenges within the DNVC process. Lastly, building upon extant research, the paper summarizes four prominent developmental directions for AI in DNVC: safety exploration, information privacy, multi-feeder collaboration, and heightened uncertainty. Corresponding solutions to each of these directions are individually discussed.
A45: ORI-053 | B45: Web of Science | C45: 1 | D45: Application of Automated Guided Vehicles in Smart Automated Warehouse Systems: A Survey | E45: Zhang, Z; Chen, J; Guo, Q | F45: 2023 | G45: JOUR | H45: CMES-COMPUTER MODELING IN ENGINEERING & SCIENCES | I45: 10.32604/cmes.2022.021451 | J45: Exclude | K45: Reinforcement learning is not the central review subject | L45: Historical eligibility assessment | M45: The historical title/abstract versus full-text split was not retained; reason reconstructed from the final scope and available record metadata. | N45: wos_final.ris
A46: ORI-046 | B46: Web of Science | C46: 1 | D46: Application of reinforcement learning in planning and operation of new power system towards carbon peaking and neutrality | E46: Sun, FY; Wang, ZW; Huang, JH; Diao, RS; Zhao, YR; Lan, T | F46: 2023 | G46: JOUR | H46: PROGRESS IN ENERGY | I46: 10.1088/2516-1083/acb987 | J46: Exclude | K46: Not an eligible review/survey publication | L46: Historical eligibility assessment | M46: The historical title/abstract versus full-text split was not retained; reason reconstructed from the final scope and available record metadata. | N46: wos_final.ris
A47: ORI-035 | B47: Web of Science | C47: 1 | D47: Applications of Agent-Based Methods in Multi-Energy Systems-A Systematic Literature Review | E47: Yao, RQ; Hu, YK; Varga, L | F47: 2023 | G47: JOUR | H47: ENERGIES | I47: 10.3390/en16052456 | J47: Exclude | K47: Reinforcement learning is not the central review subject | L47: Historical eligibility assessment | M47: The historical title/abstract versus full-text split was not retained; reason reconstructed from the final scope and available record metadata. | N47: wos_final.ris
A48: ORI-047 | B48: Web of Science | C48: 1 | D48: Applications of Artificial Intelligence and Machine learning in smart cities | E48: Ullah, Z; Al-Turjman, F; Mostarda, L; Gagliardi, R | F48: 2020 | G48: JOUR | H48: COMPUTER COMMUNICATIONS | I48: 10.1016/j.comcom.2020.02.069 | J48: Exclude | K48: Not an eligible review/survey publication | L48: Historical eligibility assessment | M48: The historical title/abstract versus full-text split was not retained; reason reconstructed from the final scope and available record metadata. | N48: wos_final.ris
A49: ORI-062 | B49: ScienceDirect | C49: 1 | D49: Applications of reinforcement learning for building energy efficiency control: A review | E49: Fu, Qiming; Han, Zhicong; Chen, Jianping; Lu, You; Wu, Hongjie; Wang, Yunzhe | F49: 2022 | G49: JOUR | H49: Journal of Building Engineering | I49: 10.1016/j.jobe.2022.104165 | J49: Include | K49: Eligible in the pre-existing coded corpus | L49: Full-text eligibility | M49: Final corpus | N49: ScienceDirect_citations_1783952383784(1).ris
A50: ORI-094 | B50: ScienceDirect | C50: 1 | D50: Applications of reinforcement learning in energy systems | E50: Perera, A.T.D.; Kamalaruban, Parameswaran | F50: 2021 | G50: JOUR | H50: Renewable and Sustainable Energy Reviews | I50: 10.1016/j.rser.2020.110618 | J50: Exclude | K50: Not an eligible review/survey publication | L50: Historical eligibility assessment | M50: The historical title/abstract versus full-text split was not retained; reason reconstructed from the final scope and available record metadata. | N50: ScienceDirect_citations_1783952383784(1).ris | O50: Energy systems undergo major transitions to facilitate the large-scale penetration of renewable energy technologies and improve efficiencies, leading to the integration of many sectors into the energy system domain. As the complexities in this domain increase, it becomes challenging to control energy flows using existing techniques based on physical models. Moreover, although data-driven models, such as reinforcement learning (RL), have gained considerable attention in many fields, a direct shift into RL is not feasible in the energy domain irrespective of the ongoing complexities. To this end, a top-down approach is used to understand this behavior by reviewing the current state of the art. We classified RL papers in the literature into seven categories based on their area of application. Subsequently, publications under each category were further examined relative to problem diversity, RL technique employed, performance improvement (compared with other white and gray box models), verification, and reproducibility; many of the articles reported a 10–20% performance improvement with the use of RL. In most studies, however, deep learning techniques and state-of-the-art actor-critic methods (e.g., twin delayed deep deterministic policy gradient and soft actor-critic) were not applied. This has remarkably hindered performance improvements and problems related to complex energy flows have not been considered. Approximately half of the publications reported the use of Q-learning. Furthermore, despite the availability of historical data in the energy system domain, batch RL algorithms have not been exploited. Emerging multi-agent RL applications may be considered as a positive development that can enable the management of complex interactions among multiple parties. Most studies lack proper benchmarking compared to model-based approaches or gray-box models, and a majority cover energy dispatch problems and building energy management. Although RL can adequately solve problems that are considerably integrated in several sectors, only a limited number of publications have discussed its broad application. The present study clearly demonstrates that even without the full utilization of RL capacity, this technique has a considerable potential in resolving the continuously increasing complexity within the energy system domain.
A51: ORI-044 | B51: Web of Science | C51: 1 | D51: Artificial Intelligence Applications in Electric Distribution Systems: Post-Pandemic Progress and Prospect | E51: Chung, SJ; Zhang, Y | F51: 2023 | G51: JOUR | H51: APPLIED SCIENCES-BASEL | I51: 10.3390/app13126937 | J51: Exclude | K51: Not an eligible review/survey publication | L51: Historical eligibility assessment | M51: The historical title/abstract versus full-text split was not retained; reason reconstructed from the final scope and available record metadata. | N51: wos_final.ris
A52: ORI-164 | B52: IEEE Xplore | C52: 1 | D52: Artificial Intelligence in the Hierarchical Control of AC, DC, and Hybrid AC/DC Microgrids: A Review | E52: J. Gutiérrez-Escalona; C. Roncero-Clemente; O. Husev; O. Matiushkin; F. Blaabjerg | F52: 2024 | G52: JOUR | H52: IEEE Access | I52: 10.1109/access.2024.3486382 | J52: Exclude | K52: Reinforcement learning is not the central review subject | L52: Historical eligibility assessment | M52: The historical title/abstract versus full-text split was not retained; reason reconstructed from the final scope and available record metadata. | N52: ieee_final.ris | O52: Growing concerns about the energy and environmental crisis are accelerating the transition to a sustainable energy generation landscape through the integration of distributed generators (DGs) into the electric power systems. Microgrids (MGs) have developed as autonomous, localized energy solutions for integrating DGs, improving grid functionality and reliability by supporting both grid-connected and islanded operational modes. Furthermore, the dc nature of numerous DGs and domestic appliances, along with advances in power electronics, have driven research away from traditional ac MGs towards dc and even hybrid ac/dc MGs. This transition introduces greater complexity and a wider range of control scenarios. To address the challenges of these increasingly complex systems, this paper reviews the application of artificial intelligence (AI) in the hierarchical control structures of ac, dc, and hybrid ac/dc MGs. AI techniques show significant promise in enhancing control and operation due to their ability to learn and adapt from the system operational data. However, integrating these AI algorithms into real-world applications remains challenging, with substantial progress still required to make these methods viable in practical scenarios. This review highlights the latest research efforts, identifies the key contributions of AI to MG control, and outlines the limitations and future research opportunities in the field.
A53: ORI-096 | B53: ScienceDirect | C53: 1 | D53: Artificial intelligence strategies applied in general and automotive air conditioning control. A review of the last 20 years | E53: Mendes, Ramon de Paoli; Pábon, Juan José Garcia; Pottie, Daniel Leon Ferreira; Machado, Luiz | F53: 2024 | G53: JOUR | H53: International Journal of Refrigeration | I53: 10.1016/j.ijrefrig.2024.03.009 | J53: Exclude | K53: Reinforcement learning is not the central review subject | L53: Historical eligibility assessment | M53: The historical title/abstract versus full-text split was not retained; reason reconstructed from the final scope and available record metadata. | N53: ScienceDirect_citations_1783952383784(1).ris | O53: This article conducts a 20-year review of studies investigating the utilization of artificial intelligence in HVAC (Heating, Ventilation, and Air Conditioning) system control, with a particular focus on automotive HVAC systems, renowned for their unique challenges due to the highly dynamic nature of automotive cabins. Artificial neural networks (ANNs) provide adaptive modeling and control capabilities to enhance energy efficiency, thermal comfort, and air quality in HVAC systems. Nevertheless, ANNs exhibit limitations, primarily their performance being constrained by training data, impeding adaptability to unforeseen scenarios. To overcome these constraints, researchers have explored hybrid approaches that integrate ANNs with PID (Proportional, Integral, and Derivative) or PI (Proportional and Integral) algorithms, resulting in systems referred to as Neuro-PID or Neuro-PI. These systems can effectively handle unanticipated situations by absorbing errors introduced by ANNs. Nonetheless, the applicability of Neuro-PID varies depending on the specific system. It becomes infeasible in scenarios with substantial delays, prompting the choice of the appropriate approach based on the controllability factor, a ratio between system delay and time constant. A controllability factor less than 2 indicates the suitability of employing ANNs for PID controller tuning. Furthermore, the intricate interaction between temperature and humidity in HVAC control systems diminishes the effectiveness of traditional PID. To proficiently regulate both variables, a viable alternative is the amalgamation of ANNs with specific control logic or the deployment of distinct ANN algorithms for varying scenarios. The heightened variability and unpredictability within automotive HVAC systems, driven by continuous vehicle movement and door/window operations, present additional challenges. In such contexts, reinforcement learning techniques have found application, allowing systems to dynamically adapt to unforeseen events. In summary, the choice of HVAC control approach hinges on the primary goal—thermal comfort or specific variable control—as well as the system's noise level, controllability factor, and system nature. While ANNs hold significant potential, combining them with other techniques, such as PID, reinforcement learning, or specific control logic, may prove essential in addressing the intricacies of HVAC systems
A54: ORI-113 | B54: ScienceDirect | C54: 1 | D54: Artificial intelligence techniques for enabling Big Data services in distribution networks: A review | E54: Barja-Martinez, Sara; Aragüés-Peñalba, Mònica; Munné-Collado, Íngrid; Lloret-Gallego, Pau; Bullich-Massagué, Eduard; Villafafila-Robles, Roberto | F54: 2021 | G54: JOUR | H54: Renewable and Sustainable Energy Reviews | I54: 10.1016/j.rser.2021.111459 | J54: Exclude | K54: Reinforcement learning is not the central review subject | L54: Historical eligibility assessment | M54: The historical title/abstract versus full-text split was not retained; reason reconstructed from the final scope and available record metadata. | N54: ScienceDirect_citations_1783952383784(1).ris | O54: Artificial intelligence techniques lead to data-driven energy services in distribution power systems by extracting value from the data generated by the deployed metering and sensing devices. This paper performs a holistic analysis of artificial intelligence applications to distribution networks, ranging from operation, monitoring and maintenance to planning. The potential artificial intelligence techniques for power system applications and needed data sources are identified and classified. The following data-driven services for distribution networks are analyzed: topology estimation, observability, fraud detection, predictive maintenance, non-technical losses detection, forecasting, energy management systems, aggregated flexibility services and trading. A review of the artificial intelligence methods implemented in each of these services is conducted. Their interdependencies are mapped, proving that multiple services can be offered as a single clustered service to different stakeholders. Furthermore, the dependencies between the AI techniques with each energy service are identified. In recent years there has been a significant rise of deep learning applications for time series prediction tasks. Another finding is that unsupervised learning methods are mainly being applied to customer segmentation, buildings efficiency clustering and consumption profile grouping for non-technical losses detection. Reinforcement learning is being widely applied to energy management systems design, although more testing in real environments is needed. Distribution network sensorization should be enhanced and increased in order to obtain larger amounts of valuable data, enabling better service outcomes. Finally, the future opportunities and challenges for applying artificial intelligence in distribution grids are discussed.
A55: ORI-107 | B55: ScienceDirect | C55: 1 | D55: Assessment and reduction of embodied carbon emissions in buildings: a systematic literature review of recent advances | E55: Shi, Yunze; Cao, Xiaodong; Yang, Xudong | F55: 2025 | G55: JOUR | H55: Energy and Buildings | I55: 10.1016/j.enbuild.2025.116058 | J55: Exclude | K55: Reinforcement learning is not the central review subject | L55: Historical eligibility assessment | M55: The historical title/abstract versus full-text split was not retained; reason reconstructed from the final scope and available record metadata. | N55: ScienceDirect_citations_1783952383784(1).ris | O55: Decarbonization of the building sector is crucial for achieving global carbon neutrality, as the industry constitutes 37 % of total greenhouse gas (GHG) emissions worldwide. While operational carbon emissions (OCE) have declined through energy efficiency advancements, embodied carbon emissions (ECE) remain challenging to address due to their complexity across multiple building lifecycle stages. Conventional Life Cycle Assessment (LCA) faces limitations in dynamic scenarios, regional variability, and system boundary inconsistencies. Following the PRISMA 2020 guidelines, we conducted a systematic review of 7,731 publications (2020–2024), ultimately analyzing 159 high-impact studies. This review employs bibliometric analysis and qualitative content analysis to identify methodological innovations and effective reduction strategies. Bibliometric analysis revealed a notable shift from traditional LCA approaches toward two pivotal paradigm shifts: (1) machine learning (ML)-driven methodologies for dynamic assessment and reduction, which leverage three fundamental learning paradigms (supervised, unsupervised, and reinforcement learning) to automate predictive modeling, uncertainty quantification, and design optimization across the building lifecycle; and (2) multi-criteria decision-making (MCDM)-based frameworks that integrate regional-specific variables to resolve the carbon-performance-cost trilemma. Case studies from diverse geographical contexts highlight the necessity of context-sensitive strategies, demonstrating how localized decarbonization pathways can reduce ECE while maintaining building performance. Key challenges include data heterogeneity and standardization gaps, interpretability limitations of advanced ML algorithms, and geospatial adaptation of MCDM frameworks. Key findings emphasize the need for hybrid ML-MCDM frameworks with enhanced explainability that deliver actionable insights for ECE reduction in diverse contexts. Future research should prioritize the development of interpretable ML models that balance computational efficiency with transparent design parameter justification, establishing unified protocols for ECE accounting across diverse contexts, and fostering cross-disciplinary partnerships.
A56: ORI-121 | B56: IEEE Xplore | C56: 1 | D56: Building Energy Management With Reinforcement Learning and Model Predictive Control: A Survey | E56: H. Zhang; S. Seal; D. Wu; F. Bouffard; B. Boulet | F56: 2022 | G56: JOUR | H56: IEEE Access | I56: 10.1109/access.2022.3156581 | J56: Include | K56: Eligible in the pre-existing coded corpus | L56: Full-text eligibility | M56: Final corpus | N56: ieee_final.ris | O56: Building energy management has been recognized as of significant importance on improving the overall system efficiency and reducing the greenhouse gas emission. However, the building energy management system is now facing more challenges and uncertainties with the increasing penetration of renewable energy and increasing adoption of different types of electrical appliances and equipment. Classical model predictive control (MPC) has shown effective in building energy management, although it suffers from labour-intensive modelling and complex online control optimization. Recently, with the growing accessibility to building control and automation data, data-driven solutions such as data-driven MPC and reinforcement learning (RL)-based methods have attracted more research interest. However, the potential of integrating these two types of methods and how to choose suitable control algorithms have not been well discussed. In this work, we first present a compact review of the recent advances in data-driven MPC and RL-based control methods for building energy management. Furthermore, the main challenges in these approaches and general discussions on the selection of control methods are discussed.
A57: ORI-114 | B57: ScienceDirect | C57: 1 | D57: Building simulation in adaptive training of machine learning models | E57: Amini, Hamed; Alanne, Kari; Kosonen, Risto | F57: 2024 | G57: JOUR | H57: Automation in Construction | I57: 10.1016/j.autcon.2024.105564 | J57: Exclude | K57: Not an eligible review/survey publication | L57: Historical eligibility assessment | M57: The historical title/abstract versus full-text split was not retained; reason reconstructed from the final scope and available record metadata. | N57: ScienceDirect_citations_1783952383784(1).ris | O57: Combining building performance simulation (BPS) and artificial intelligence (AI) provides smart buildings with the ability to adapt by utilizing BPS's data synthesis and training capabilities. There is a scarcity of comprehensive reviews focusing on how building simulation contributes to the adaptation process. The contribution of this review is to analyze the implementation of building simulation in adaptive (AI) systems as both data acquisition and training environments, by interpreting adaptation as a cyclical process. Here, the reviewed studies are classified into four major applications: prediction, optimization, control, and management. It is concluded that defining adaptation as a cyclical process provides a useful framework for the development of adaptive smart buildings. Among the reviewed control and management applications, 48% of decision-making AI agents were trained adaptively, with contributions from BPS. Further research is needed to fully exploit the potential of BPS in training decision-making AI especially when aiming at continuous (cyclical) adaptation.
A58: ORI-110 | B58: ScienceDirect | C58: 1 | D58: Chapter 6 - Hybrid energy storages in buildings with artificial intelligence | E58: Sun, Ying; Liu, Zhengxuan | F58: 2024 | G58: CHAP | H58: Advances in Digitalization and Machine Learning for Integrated Building-Transportation Energy Systems | I58: 10.1016/b978-0-443-13177-6.00004-7 | J58: Exclude | K58: Not an eligible review/survey publication | L58: Historical eligibility assessment | M58: The historical title/abstract versus full-text split was not retained; reason reconstructed from the final scope and available record metadata. | N58: ScienceDirect_citations_1783952383784(1).ris | O58: Energy storage systems (ESSs) integrated in buildings not only ease the stress on grids through peak shifting and peak shaving, but also contribute to solving the mismatch between supply and demand by storing renewable energy for later use. With the rapid expansion of available data, artificial intelligence has been widely applied in the prediction, optimization, and control of hybrid ESS in buildings. This chapter summarizes the commonly used ESS in buildings, such as water tanks, batteries, building-integrated thermal ESSs, and underground/underwater ESSs. Besides, AI-based prediction methods (i.e., supervised machine learning algorithms) and optimization technologies (e.g., genetic algorithms, particle swarm optimization, differential evolution, ant colony optimization, simulated annealing, immune algorithms, and artificial fish swarm algorithms), control strategies, including AI-based model predictive controllers and predictive-free controllers (i.e., reinforcement learning), have been introduced. The advantages and disadvantages of AI technologies are also compared. In addition, we have reviewed the existing studies on the application of AI technologies to ESS in buildings to predict the energy storage capacity and rates, optimize the design parameters, and control the charge/discharge rate. Based on the discussion of existing studies, potential future research directions are given.
A59: ORI-076 | B59: ScienceDirect | C59: 1 | D59: Collaborative swarm robotics for sustainable environment monitoring and exploration: Emerging trends and research progress | E59: Khaldi, Belkacem; Harrou, Fouzi; Sun, Ying | F59: 2025 | G59: JOUR | H59: Energy Nexus | I59: 10.1016/j.nexus.2025.100365 | J59: Exclude | K59: Not an eligible review/survey publication | L59: Historical eligibility assessment | M59: The historical title/abstract versus full-text split was not retained; reason reconstructed from the final scope and available record metadata. | N59: ScienceDirect_citations_1783952383784(1).ris | O59: This study explores the application of swarm robotics and swarm and evolutionary computing techniques in environmental management and sustainability, a highly specific and increasingly demanding niche research area. Through a bibliometric analysis of two collections of peer-reviewed papers, key trends and emerging research areas are identified. The first collection, comprising approximately 450 papers, focuses on specific applications of swarm robotics systems in environmental use cases, including swarms of UAVs, AUVs, and USVs, particularly in tasks such as ecological monitoring, agricultural management, and disaster response. This analysis highlights essential keyword clusters, with ``ecological restoration'' emerging as a significant topic, and ``agricultural robots'' and ``remote sensing'' as active frontiers. Building on this analysis, eight directions are proposed to address environmental challenges across five categories. The second collection, consisting of around 198 papers, examines the different swarm and evolutionary computing algorithms employed in this niche area, identifying ten significant research clusters. Notably, the ``secure incentive mechanism'' is a trending area, emphasizing the development of reliable and secure cooperative multi-robot systems. Recent methods in this cluster utilize deep reinforcement learning and heuristic algorithms to enhance cooperation efficiency. Five potential directions categorized into two main groups are explored to address security and reliability challenges within swarm robot systems in environmental tasks. The findings underscore the critical role of swarm robotics in environment-focused tasks such as ecosystem recovery and the importance of secure cooperation mechanisms, paving the way for advancements in agriculture, resource management, intelligent infrastructure, and urban systems.
A60: ORI-153 | B60: IEEE Xplore | C60: 1 | D60: Collective Intelligence and Application Potentials in Modern Power Systems: A Comprehensive Review | E60: T. Pu; J. Cao; X. Wang; D. Zhang | F60: 2026 | G60: JOUR | H60: CSEE Journal of Power and Energy Systems | I60: 10.17775/cseejpes.2025.02500 | J60: Exclude | K60: Reinforcement learning is not the central review subject | L60: Historical eligibility assessment | M60: The historical title/abstract versus full-text split was not retained; reason reconstructed from the final scope and available record metadata. | N60: ieee_final.ris | O60: Modern power systems serve as a critical component of new energy architectures and are essential carriers for achieving the dual carbon goals. With the increasing penetration of renewable energy and the widespread use of various flexible, uncertain, distributed energy resources, the variety of generation and load types in power systems continues to expand, resulting in greater operational complexity and control challenges. Collective intelligence, identified as one of the key research directions in China's next generation artificial intelligence development plan, can leverage multi-agent cooperative optimization to support coordinated optimization and control in modern power systems. This paper begins with a brief overview of collective intelligence technologies. The current state of key research scenarios in modern power systems is then analyzed, with a focus on the emerging features and challenges encountered in these environments. Subsequently, the application potential of collective intelligence in modern power systems is summarized, along with a review of relevant research efforts in this domain. Finally, future research directions are discussed, highlighting advanced technologies that are expected to further enhance the integration of collective intelligence into modern power system control and optimization.
A61: ORI-125 | B61: IEEE Xplore | C61: 1 | D61: Comparative Analysis of Control Strategies for Microgrid Energy Management with a Focus on Reinforcement Learning | E61: P. Mohammadi; R. Darshi; S. Shamaghdari; P. Siano | F61: 2024 | G61: JOUR | H61: IEEE Access | I61: 10.1109/access.2024.3495032 | J61: Exclude | K61: Not an eligible review/survey publication | L61: Historical eligibility assessment | M61: The historical title/abstract versus full-text split was not retained; reason reconstructed from the final scope and available record metadata. | N61: ieee_final.ris | O61: The depletion of fossil fuel reserves and the urgent need to cut greenhouse gas emissions are driving a significant shift in the global energy sector. This transformation necessitates advanced energy management strategies in microgrids to integrate renewable energy sources efficiently. Traditional methods, including classical, metaheuristic, model predictive, stochastic, and robust control techniques, have been extensively studied. However, these approaches often struggle with slow performance and high computational demands, making them less effective for real-time applications due to the need for frequent re-optimization. In contrast, reinforcement learning, a branch of machine learning, excels by continuously learning and optimizing through real-time interactions This approach offers greater flexibility and adaptability in complex and dynamic environments. This paper provides a comparative review of various control strategies for microgrid energy management, examining their strengths and limitations. We place a particular focus on reinforcement learning algorithms and their application in microgrids. This paper conducts a detailed analysis of studies on reinforcement learning-based energy management systems, evaluating their potential to enhance energy efficiency, optimize usage, and contribute to the sustainability of modern energy infrastructures. This review aims to enhance understanding in this field and offer insights for future research on smart energy management systems.
A62: ORI-137 | B62: IEEE Xplore | C62: 1 | D62: Comprehensive Analysis of Fuel Cell Electric Vehicles: Challenges, Powertrain Configurations, and Energy Management Systems | E62: M. S. Munsi; R. P. Joshi | F62: 2024 | G62: JOUR | H62: IEEE Access | I62: 10.1109/access.2024.3472704 | J62: Exclude | K62: Not an eligible review/survey publication | L62: Historical eligibility assessment | M62: The historical title/abstract versus full-text split was not retained; reason reconstructed from the final scope and available record metadata. | N62: ieee_final.ris | O62: Rising concerns about fuel costs, emissions, oil depletion, and energy security have propelled the search for alternative energy sources in transportation. Electric vehicles are a crucial development in this direction, and fuel cell technology is gaining traction for its versatility and potential benefits. Fuel cells have become increasingly attractive for automobile owing to their ease of use, quiet operation, superior efficiency, modular design, and reliance on clean hydrogen. However, challenges remain, including hydrogen storage, high costs, integration with power electronics, and cold-start capabilities, which continue to impede the widespread adoption of Fuel Cell Electric Vehicles (FCEVs). This study critically examines these key issues, explores various fuel cell technologies and drivetrain architectures, and provides a comparative analysis of different energy storage systems. Furthermore, the study delves into the classification and evaluation of energy management strategies (EMS) for FCEVs. The review ultimately aims to stimulate further research focused on reducing costs, extending fuel cell lifespan, enhancing hydrogen infrastructure, optimizing electronic interfaces, and refining EMS to pave the way for the future of FCEVs.
A63: ORI-156 | B63: IEEE Xplore | C63: 1 | D63: Comprehensive Review on the Control of Heat Pumps for Energy Flexibility in Distribution Networks | E63: G. L. Aschidamini; M. Pavlovic; B. A. Reinholz; M. S. Metcalfe; T. Niet; M. Resener | F63: 2025 | G63: JOUR | H63: IEEE Access | I63: 10.1109/access.2025.3569761 | J63: Exclude | K63: Reinforcement learning is not the central review subject | L63: Historical eligibility assessment | M63: The historical title/abstract versus full-text split was not retained; reason reconstructed from the final scope and available record metadata. | N63: ieee_final.ris | O63: Decarbonization plans promote the transition to heat pumps (HPs), creating new opportunities for their energy flexibility in demand response programs, solar photovoltaic integration, and optimization of distribution networks. This paper reviews scheduling-based and real-time optimization methods for controlling HPs with a focus on energy flexibility in distribution networks. Scheduling-based methods fall into two categories: rule-based controllers (RBCs), which rely on predefined control rules without explicitly seeking optimal solutions, and optimization models, which are designed to determine the optimal scheduling of operations. Real-time optimization is achieved through model predictive control (MPC), which relies on a predictive model to optimize decisions over a time horizon, and reinforcement learning (RL), which takes a model-free approach by learning optimal strategies through direct interaction with the environment. The paper also examines studies on the impact of HPs on distribution networks, particularly those leveraging energy flexibility strategies. Key takeaways suggest the need to validate control strategies for extreme cold-weather regions that require backup heaters, as well as develop approaches designed for demand charge schemes that integrate HPs with other controllable loads. From a grid impact assessment perspective, studies have focused primarily on RBCs for providing energy flexibility through HP operation, without addressing more advanced methods such as real-time optimization using MPC or RL-based algorithms. Incorporating these advanced control strategies could help identify key limitations, including the impact of varying user participation levels and the cost-benefit trade-offs associated with their implementation.
A64: ORI-092 | B64: ScienceDirect | C64: 1 | D64: Concepts of user-centred lighting controls for office applications: A systematic literature review | E64: Hammes, Sascha; Geisler-Moroder, David; Hauer, Martin; Weninger, Johannes; Obleitner, Maximilian; Miller, Josef; Plörer, Daniel; Van Karsbergen, Vincent; Weitlaner, Robert; Pfluger, Rainer | F64: 2024 | G64: JOUR | H64: Building and Environment | I64: 10.1016/j.buildenv.2024.111321 | J64: Exclude | K64: Reinforcement learning is not the central review subject | L64: Historical eligibility assessment | M64: The historical title/abstract versus full-text split was not retained; reason reconstructed from the final scope and available record metadata. | N64: ScienceDirect_citations_1783952383784(1).ris | O64: Due to the very limited information available during building design phase, lighting automation systems tend to follow pre-defined control curves and use normative default values. However, these are unlikely to reflect the wide variation in daily working hours and individual lighting preferences. Inadequate user modelling can result in missed energy and comfort targets, as well as insufficient light doses. Given that the building sector accounts for around one third of the world's energy demand, and lighting is one of the main consumers, a higher level of user representation in lighting control systems is essential to meet climate and environmental targets. The general practical applicability of user-centred concepts usually fails due to implementation, inadequate mapping of objectives to required parameters, availability of information and mapping in control systems. This comprehensive literature review of 160 articles evaluates the potential of individual control concepts in relation to the target criteria of lighting systems and identifies the necessary technical system components for greater applicability. The focus of the review is on daylight and artificial lighting and their application in office environments. From the results obtained, key elements for better implementation of user-centred concepts in lighting control were derived. These include zoned lighting, human-in-the-loop approaches, and sensor fusion. Post-occupancy evaluation, supported by social science methods, can help to capture relevant physiological and psychological parameters. The review concludes that post-occupancy optimisation of user-centred lighting applications offers great potential for overcoming previous design limitations and subsequently reducing performance gaps.
A65: ORI-041 | B65: Web of Science | C65: 1 | D65: Control strategies for integration of thermal energy storage into buildings: State-of-the-art review | E65: Yu, Z; Huang, GS; Haghighat, F; Li, HQ; Zhang, GQ | F65: 2015 | G65: JOUR | H65: ENERGY AND BUILDINGS | I65: 10.1016/j.enbuild.2015.05.038 | J65: Exclude | K65: Reinforcement learning is not the central review subject | L65: Historical eligibility assessment | M65: The historical title/abstract versus full-text split was not retained; reason reconstructed from the final scope and available record metadata. | N65: wos_final.ris
A66: ORI-055 | B66: Web of Science | C66: 1 | D66: Convergence of Photovoltaic Power Forecasting and Deep Learning: State-of-Art Review | E66: Massaoudi, M; Chihi, I; Abu-Rub, H; Refaat, SS; Oueslati, FS | F66: 2021 | G66: JOUR | H66: IEEE ACCESS | I66: 10.1109/access.2021.3117004 | J66: Exclude | K66: Reinforcement learning is not the central review subject | L66: Historical eligibility assessment | M66: The historical title/abstract versus full-text split was not retained; reason reconstructed from the final scope and available record metadata. | N66: wos_final.ris
A67: ORI-067 | B67: ScienceDirect | C67: 1 | D67: Corrigendum to “Multi objectives reinforcement learning for smart buildings: A systematic review of algorithms, applications and future perspectives” [Energy Build. 345 (2025) 116045] | E67: Yen Huynh, Thi Ngoc; Nguyen, Anh Tuan; Ahn, Yonghan; Oo, Bee Lan; Lim, Benson T.H. | F67: 2025 | G67: JOUR | H67: Energy and Buildings | I67: 10.1016/j.enbuild.2025.116068 | J67: Exclude | K67: Did not satisfy all centrality, publication-type, or scope criteria in the final eligibility assessment | L67: Historical eligibility assessment | M67: The historical title/abstract versus full-text split was not retained; reason reconstructed from the final scope and available record metadata. | N67: ScienceDirect_citations_1783952383784(1).ris
A68: ORI-049 | B68: Web of Science | C68: 1 | D68: Data-Driven Analytics for Reliability in the Buildings-to-Grid Integrated System Framework: A Systematic Text-Mining-Assisted Literature Review and Trend Analysis | E68: Bachoumis, A; Mylonas, C; Plakas, K; Birbas, M; Birbas, A | F68: 2023 | G68: JOUR | H68: IEEE ACCESS | I68: 10.1109/access.2023.3335191 | J68: Exclude | K68: Reinforcement learning is not the central review subject | L68: Historical eligibility assessment | M68: The historical title/abstract versus full-text split was not retained; reason reconstructed from the final scope and available record metadata. | N68: wos_final.ris
A69: ORI-040 | B69: Web of Science | C69: 1 | D69: Data-driven energy management of virtual power plants: A review | E69: Ruan, GC; Qiu, DW; Sivaranjani, S; Awad, ASA; Strbac, G | F69: 2024 | G69: JOUR | H69: ADVANCES IN APPLIED ENERGY | I69: 10.1016/j.adapen.2024.100170 | J69: Exclude | K69: Reinforcement learning is not the central review subject | L69: Historical eligibility assessment | M69: The historical title/abstract versus full-text split was not retained; reason reconstructed from the final scope and available record metadata. | N69: wos_final.ris
A70: ORI-057 | B70: ScienceDirect | C70: 1 | D70: Data-driven methods for building control — A review and promising future directions | E70: Maddalena, Emilio T.; Lian, Yingzhao; Jones, Colin N. | F70: 2020 | G70: JOUR | H70: Control Engineering Practice | I70: 10.1016/j.conengprac.2019.104211 | J70: Exclude | K70: Reinforcement learning is not the central review subject | L70: Historical eligibility assessment | M70: The historical title/abstract versus full-text split was not retained; reason reconstructed from the final scope and available record metadata. | N70: ScienceDirect_citations_1783952383784(1).ris
A71: ORI-024 | B71: Web of Science; ScienceDirect | C71: 2 | D71: Data-driven methods for the reduction of energy consumption in warehouses: Use-case driven analysis | E71: Shaer, Ibrahim; Shami, Abdallah | F71: 2023 | G71: JOUR | H71: Internet of Things | I71: 10.1016/j.iot.2023.100882 | J71: Exclude | K71: Not an eligible review/survey publication | L71: Historical eligibility assessment | M71: The historical title/abstract versus full-text split was not retained; reason reconstructed from the final scope and available record metadata. | N71: wos_final.ris; ScienceDirect_citations_1783952383784(1).ris | O71: On a global scale, buildings account for a significant portion of energy consumption and CO2 emissions, contributing to inclement environmental conditions. The Heating, Ventilation, and Air Conditioning (HVAC) system is an important energy consumer in buildings, which can be controlled to reduce overall energy consumption. This paper provides an overview of the HVAC control problem for energy reduction in warehouses. In particular, this paper first introduces the enabling technologies for HVAC control. After that, an extensive explanation of the warehouse environment is provided. Issues such as multi-zone spaces, occupancy profiling, and ambient environmental conditions are highlighted in connection to energy consumption. Next, a survey of traditional solutions followed by the proposed solution of incorporating Reinforcement Learning (RL) and Supervised Learning techniques are discussed. After that, an in-depth summary of the challenges associated with the implementation of these techniques is examined. Lastly, a use case study is conducted to demonstrate the outlined challenges using a dataset collected in a real-world environment.
A72: ORI-090 | B72: ScienceDirect | C72: 1 | D72: Data-driven policy mapping for safe RL-based energy management systems | E72: Zangato, Théo; Osmani, Aomar; Alizadeh, Pegah | F72: 2025 | G72: JOUR | H72: Energy Reports | I72: 10.1016/j.egyr.2025.01.002 | J72: Exclude | K72: Not an eligible review/survey publication | L72: Historical eligibility assessment | M72: The historical title/abstract versus full-text split was not retained; reason reconstructed from the final scope and available record metadata. | N72: ScienceDirect_citations_1783952383784(1).ris | O72: Increasing global energy demand and renewable integration complexity have placed buildings at the center of sustainable energy management. We present a three-step reinforcement learning (RL)-based Building Energy Management System (BEMS) that combines clustering, forecasting, and constrained policy learning to address scalability, adaptability, and safety challenges. First, we cluster non-shiftable load profiles to identify common consumption patterns, enabling policy generalization and transfer without retraining for each new building. Next, we integrate an LSTM-based forecasting module to anticipate future states, improving the RL agent’s responsiveness to dynamic conditions. Lastly, domain-informed action masking ensures safe exploration and operation, preventing harmful decisions. Evaluated on real-world data, our approach reduces operating costs by up to 15% for certain building types, maintains stable environmental performance, and quickly classifies and optimizes new buildings with limited data. It also adapts to stochastic tariff changes without retraining. Overall, this framework delivers scalable, robust, and cost-effective building energy management.
A73: ORI-074 | B73: ScienceDirect | C73: 1 | D73: Data-driven wind farm flow control and challenges towards field implementation: A review | E73: Göçmen, Tuhfe; Liew, Jaime; Kadoche, Elie; Dimitrov, Nikolay; Riva, Riccardo; Andersen, Søren Juhl; Lio, Alan W.H.; Quick, Julian; Réthoré, Pierre-Elouan; Dykes, Katherine | F73: 2025 | G73: JOUR | H73: Renewable and Sustainable Energy Reviews | I73: 10.1016/j.rser.2025.115605 | J73: Exclude | K73: Reinforcement learning is not the central review subject | L73: Historical eligibility assessment | M73: The historical title/abstract versus full-text split was not retained; reason reconstructed from the final scope and available record metadata. | N73: ScienceDirect_citations_1783952383784(1).ris | O73: Data-driven wind farm flow control (WFFC) is an innovative approach that leverages the collected data and advanced analytics to enhance the performance of wind turbines within wind farms. Its significance lies in its ability to adapt to changing wind and turbine conditions and improve operations, boosting energy yield, extending turbine/component lifetime, and potentially reducing socio-environmental impact and costs, thus supporting the viability and sustainability of wind energy as a renewable power source. This review explores the dynamic field of data-driven WFFC and its challenges towards practical implementation. Building on top of traditional wind farm modelling and model-based control, it details the virtues and limitations of these methods while introducing the concept of data-informed or data-driven flow models that harness data to augment predictive accuracy and control strategies. The analysis then covers the methodologies for power and load surrogates, elucidating the pivotal role of surrogate modelling in enhancing WFFC, and showcasing its value in decision-making and energy optimisation. Furthermore, the growing field of reinforcement learning (RL) is highlighted, showcasing its adaptive potential to revolutionise wind farm control through learning from past interactions. The investigation concludes by identifying key challenges impeding the practical deployment of data-driven WFFC, including data quality concerns, cybersecurity risks, and limitations of the current algorithms. In summary, this comprehensive review presents the ongoing development of data-driven WFFC, emphasising the synergy between traditional methods, surrogate modelling, RL, and the critical challenges to be addressed for successful integration of these methodologies in real-world wind farm operations.
A74: ORI-051 | B74: Web of Science | C74: 1 | D74: Deep deterministic policy gradient algorithm: A systematic review | E74: Sumiea, EH; Abdulkadir, SJ; Alhussian, HS; Al-Selwi, SM; Alqushaibi, A; Ragab, MG; Fati, SM | F74: 2024 | G74: JOUR | H74: HELIYON | I74: 10.1016/j.heliyon.2024.e30697 | J74: Exclude | K74: Reinforcement learning is not the central review subject | L74: Historical eligibility assessment | M74: The historical title/abstract versus full-text split was not retained; reason reconstructed from the final scope and available record metadata. | N74: wos_final.ris
A75: ORI-056 | B75: Web of Science | C75: 1 | D75: Deep learning in power systems research: A review | E75: Khodayar, M; Liu, GY; Wang, JH; Khodayar, ME | F75: 2021 | G75: JOUR | H75: CSEE JOURNAL OF POWER AND ENERGY SYSTEMS | I75: 10.17775/cseejpes.2020.02700 | J75: Exclude | K75: Reinforcement learning is not the central review subject | L75: Historical eligibility assessment | M75: The historical title/abstract versus full-text split was not retained; reason reconstructed from the final scope and available record metadata. | N75: wos_final.ris
A76: ORI-161 | B76: IEEE Xplore | C76: 1 | D76: Deep Learning in Smart Grid Technology: A Review of Recent Advancements and Future Prospects | E76: M. Massaoudi; H. Abu-Rub; S. S. Refaat; I. Chihi; F. S. Oueslati | F76: 2021 | G76: JOUR | H76: IEEE Access | I76: 10.1109/access.2021.3071269 | J76: Exclude | K76: Reinforcement learning is not the central review subject | L76: Historical eligibility assessment | M76: The historical title/abstract versus full-text split was not retained; reason reconstructed from the final scope and available record metadata. | N76: ieee_final.ris | O76: The current electric power system witnesses a significant transition into Smart Grids (SG) as a promising landscape for high grid reliability and efficient energy management. This ongoing transition undergoes rapid changes, requiring a plethora of advanced methodologies to process the big data generated by various units. In this context, SG stands tied very closely to Deep Learning (DL) as an emerging technology for creating a more decentralized and intelligent energy paradigm while integrating high intelligence in supervisory and operational decision-making. Motivated by the outstanding success of DL-based prediction methods, this article attempts to provide a thorough review from a broad perspective on the state-of-the-art advances of DL in SG systems. Firstly, a bibliometric analysis has been conducted to categorize this review's methodology. Further, we taxonomically delve into the mechanism behind some of the trending DL algorithms. We then showcase the DL enabling technologies in SG, such as federated learning, edge intelligence, and distributed computing. Finally, challenges and research frontiers are provided to serve as guidelines for future work in the futuristic power grid domain. This study's core objective is to foster the synergy between these two fields for decision-makers and researchers to accelerate DL's practical deployment for SG systems.
A77: ORI-030 | B77: Web of Science | C77: 1 | D77: Deep reinforcement learning based energy management strategies for electrified vehicles: Recent advances and perspectives | E77: He, HW; Meng, XF; Wang, Y; Khajepour, A; An, XW; Wang, RG; Sun, FC | F77: 2024 | G77: JOUR | H77: RENEWABLE & SUSTAINABLE ENERGY REVIEWS | I77: 10.1016/j.rser.2023.114248 | J77: Exclude | K77: Not an eligible review/survey publication | L77: Historical eligibility assessment | M77: The historical title/abstract versus full-text split was not retained; reason reconstructed from the final scope and available record metadata. | N77: wos_final.ris
A78: ORI-123 | B78: IEEE Xplore | C78: 1 | D78: Deep Reinforcement Learning for Intelligent Energy Management Systems of Hybrid-Electric Powertrains: Recent Advances, Open Issues, and Prospects | E78: Y. Li; H. He; A. Khajepour; Y. Chen; W. Huo; H. Wang | F78: 2024 | G78: JOUR | H78: IEEE Transactions on Transportation Electrification | I78: 10.1109/tte.2024.3377809 | J78: Exclude | K78: Not an eligible review/survey publication | L78: Historical eligibility assessment | M78: The historical title/abstract versus full-text split was not retained; reason reconstructed from the final scope and available record metadata. | N78: ieee_final.ris | O78: The hybrid-electric powertrain presents an immediate solution to energy and environmental challenges encountered within the realm of transportation. Targeting the optimization of hybrid-electric powertrains, deep reinforcement learning (DRL) has been intensively and increasingly investigated to develop intelligent energy management systems in the context of augmented vehicular and traffic information. After a brief introduction to the Markov decision process and DRL, this article presents a comprehensive survey of the recent advancements in DRL-based energy management. The survey categorizes the progress based on the various roles that DRL plays in energy management systems, highlighting the flexibility and advantages of integrating DRL for achieving energy efficiency, safety, and reliable performance. Furthermore, the study concludes with an analysis of open issues and future prospects, including the learning and application of DRL-based energy management strategies, the development of novel DRL algorithms, and the integration of DRL-based energy management in intelligent and sustainable transportation contexts.
A79: ORI-139 | B79: IEEE Xplore | C79: 1 | D79: Deep reinforcement learning for power system applications: An overview | E79: Z. Zhang; D. Zhang; R. C. Qiu | F79: 2020 | G79: JOUR | H79: CSEE Journal of Power and Energy Systems | I79: 10.17775/cseejpes.2019.00920 | J79: Exclude | K79: Building control is not the central application domain | L79: Historical eligibility assessment | M79: The historical title/abstract versus full-text split was not retained; reason reconstructed from the final scope and available record metadata. | N79: ieee_final.ris | O79: Due to increasing complexity, uncertainty and data dimensions in power systems, conventional methods often meet bottlenecks when attempting to solve decision and control problems. Therefore, data-driven methods toward solving such problems are being extensively studied. Deep reinforcement learning (DRL) is one of these data-driven methods and is regarded as real artificial intelligence (AI). DRL is a combination of deep learning (DL) and reinforcement learning (RL). This field of research has been applied to solve a wide range of complex sequential decision-making problems, including those in power systems. This paper firstly reviews the basic ideas, models, algorithms and techniques of DRL. Applications in power systems such as energy management, demand response, electricity market, operational control, and others are then considered. In addition, recent advances in DRL including the combination of RL with other classical methods, and the prospect and challenges of applications in power systems are also discussed.
A80: ORI-157 | B80: IEEE Xplore | C80: 1 | D80: Digital Twin Integration With Data Fusion for Enhanced Photovoltaic System Management: A Systematic Literature Review | E80: J. Yuan; J. Ma; Z. Tian; K. L. Man | F80: 2024 | G80: JOUR | H80: IEEE Open Journal of Power Electronics | I80: 10.1109/ojpel.2024.3422021 | J80: Exclude | K80: Reinforcement learning is not the central review subject | L80: Historical eligibility assessment | M80: The historical title/abstract versus full-text split was not retained; reason reconstructed from the final scope and available record metadata. | N80: ieee_final.ris | O80: The integration of Digital Twin (DT) technology into the photovoltaic (PV) sector represents a significant advancement in energy management, optimization, servicing, and maintenance. This comprehensive literature review aims to enhance understanding, categorization, and adoption of DT and data fusion technologies within the PV industry to guide future research endeavors. The review categorizes PV models into three types: digital models, digital shadows, and digital twins, based on their data connection and integration attributes. It recognizes data fusion as the critical enabling technology for the development of complex DT models and proposes a framework for integrating data fusion with DT systems. A detailed examination of prevalent PV modeling methodologies is conducted to delineate their advantages and limitations, serving as a valuable resource for industry practitioners. The paper concludes that digital models and digital shadows are effective for initial PV system forecast and monitoring, while fully integrated DT models offer significant advantages, including real-time analysis, predictive capabilities, and active system optimization. However, implementing and maintaining DT models require advanced data analytics, high computational costs, and robust system security, presenting important challenges to be addressed in future research endeavors.
A81: ORI-167 | B81: IEEE Xplore | C81: 1 | D81: Distributed Control Strategies for Microgrids: A Critical Review of Technologies and Challenges | E81: G. Ahmad; A. Hassan; A. Islam; M. Shafiullah; M. A. Abido; M. Al-Dhaifallah | F81: 2025 | G81: JOUR | H81: IEEE Access | I81: 10.1109/access.2025.3552940 | J81: Exclude | K81: Reinforcement learning is not the central review subject | L81: Historical eligibility assessment | M81: The historical title/abstract versus full-text split was not retained; reason reconstructed from the final scope and available record metadata. | N81: ieee_final.ris | O81: The surging growth of the global energy demand, rapid depletion of fuel reserves, and, most importantly, increasing global warming trends have been the major concerns for decision-makers for the last couple of decades. The current prevalent renewable and clean power sources such as wind, hydro, and solar energy provide workable solutions to the foregoing problems via (DGs). Microgrids (MGs) are essential for interfacing the major portion of renewable energy sources and decision-making regarding the control and operation modes. Recent MG research trends focused on integrating those affordable and cost-effective resources into the energy mix at a consumer level. Still, due to the complexity of DG integration into the MG, many research efforts have been made to examine and develop distributed control (DCT) systems for alternating current, direct current, and hybrid MGs, and adherents of this approach, the distributed controllers have numerous advantages compared with centralized and decentralized control methods, such as increased reliability, flexibility, controllability, possibility to initiate operations independently, and robustness to communication failures. This research critically reviews the DCT strategies developed for MGs, presents various MG control strategies, and delves into different approaches to designing distributed controllers. Besides, this article highlights existing challenges and possible ways of mitigation, most especially by using artificial intelligence approaches. It also reviews the multi-microgrid concept to shed light on modern technologies and their potential applications in MGs. It is expected that the decision-makers and the researchers will find the critical analysis of this article useful while delving into various control strategies for MG.
A82: ORI-039 | B82: Web of Science | C82: 1 | D82: Driving conditions-driven energy management strategies for hybrid electric vehicles: A review | E82: Liu, T; Tan, WH; Tang, XL; Zhang, JW; Xing, Y; Cao, DP | F82: 2021 | G82: JOUR | H82: RENEWABLE & SUSTAINABLE ENERGY REVIEWS | I82: 10.1016/j.rser.2021.111521 | J82: Exclude | K82: Reinforcement learning is not the central review subject | L82: Historical eligibility assessment | M82: The historical title/abstract versus full-text split was not retained; reason reconstructed from the final scope and available record metadata. | N82: wos_final.ris
A83: ORI-063 | B83: ScienceDirect | C83: 1 | D83: Dynamic indoor thermal environment using Reinforcement Learning-based controls: Opportunities and challenges | E83: Chatterjee, Arnab; Khovalyg, Dolaana | F83: 2023 | G83: JOUR | H83: Building and Environment | I83: 10.1016/j.buildenv.2023.110766 | J83: Include | K83: Eligible in the pre-existing coded corpus | L83: Full-text eligibility | M83: Final corpus | N83: ScienceDirect_citations_1783952383784(1).ris
A84: ORI-025 | B84: Web of Science; ScienceDirect | C84: 2 | D84: Dynamic thermal environment management technologies for data center: A review | E84: Du, Yahui; Zhou, Zhihua; Yang, Xiaochen; Yang, Xueqing; Wang, Cheng; Liu, Junwei; Yuan, Jianjuan | F84: 2023 | G84: JOUR | H84: Renewable and Sustainable Energy Reviews | I84: 10.1016/j.rser.2023.113761 | J84: Exclude | K84: Reinforcement learning is not the central review subject | L84: Historical eligibility assessment | M84: The historical title/abstract versus full-text split was not retained; reason reconstructed from the final scope and available record metadata. | N84: wos_final.ris; ScienceDirect_citations_1783952383784(1).ris | O84: The energy demand of the data center (DC) industry has accounted for 2% of the total global energy consumption, and its operating power consumption has reached 50 times that of the commercial buildings. Therefore, improving the thermal environment performance to reduce the energy cost is major trend to realize the energy savings of DC. It has become a positive measure to integrate smart technologies to improve the operating efficiency of HVAC systems, especially due to the development of informatization and intelligence. This study provides detailed overview of the dynamic thermal environment management technologies of the DCs. The requirements of thermal environment in DCs were reviewed by different levels, which are the basis of the design and operation. Accordingly, various dynamic prediction technologies were presented concerning the theoretical mechanics, the computation efficiency and the applicable circumstances. The performance of the PID, the model predictive control and the reinforcement learning in the dynamic thermal environment control of DC were analyzed. Moreover, the evaluation systems based on cooling capacity, exergy analysis and entransy analysis were introduced respectively to measure the performance of the thermal environment. By investigating the knowledge related to the “requirement, prediction, control, and evaluation” of the DC dynamic thermal environment, this study aims to provide reference and guidance for energy conservation, airflow organization and smart operation of DCs.
A85: ORI-103 | B85: ScienceDirect | C85: 1 | D85: Edge AI for Internet of Energy: Challenges and perspectives | E85: Himeur, Yassine; Sayed, Aya Nabil; Alsalemi, Abdullah; Bensaali, Faycal; Amira, Abbes | F85: 2024 | G85: JOUR | H85: Internet of Things | I85: 10.1016/j.iot.2023.101035 | J85: Exclude | K85: Not an eligible review/survey publication | L85: Historical eligibility assessment | M85: The historical title/abstract versus full-text split was not retained; reason reconstructed from the final scope and available record metadata. | N85: ScienceDirect_citations_1783952383784(1).ris | O85: The digital landscape of the Internet of Energy (IoE) is on the brink of a revolutionary transformation with the integration of edge Artificial Intelligence (AI). This comprehensive review elucidates the promise and potential that edge AI holds for reshaping the IoE ecosystem. Commencing with a meticulously curated research methodology, the article delves into the myriad of edge AI techniques specifically tailored for IoE. The myriad benefits, spanning from reduced latency and real-time analytics to the pivotal aspects of information security, scalability, and cost-efficiency, underscore the indispensability of edge AI in modern IoE frameworks. As the narrative progresses, readers are acquainted with pragmatic applications and techniques, highlighting on-device computation, secure private inference methods, and the avant-garde paradigms of AI training on the edge. A critical analysis follows, offering a deep dive into the present challenges including security concerns, computational hurdles, and standardization issues. However, as the horizon of technology ever expands, the review culminates in a forward-looking perspective, envisaging the future symbiosis of 5G networks, federated edge AI, deep reinforcement learning, and more, painting a vibrant panorama of what the future beholds. For anyone vested in the domains of IoE and AI, this review offers both a foundation and a visionary lens, bridging the present realities with future possibilities.
A86: ORI-162 | B86: IEEE Xplore | C86: 1 | D86: Edge Intelligence for Smart Grid: A Survey on Application Potentials | E86: H. B. Gooi; T. Wang; Y. Tang | F86: 2023 | G86: JOUR | H86: CSEE Journal of Power and Energy Systems | I86: 10.17775/cseejpes.2022.02210 | J86: Exclude | K86: Reinforcement learning is not the central review subject | L86: Historical eligibility assessment | M86: The historical title/abstract versus full-text split was not retained; reason reconstructed from the final scope and available record metadata. | N86: ieee_final.ris | O86: With the booming of artificial intelligence (AI), Internet of Things (IoT), and high-speed communication technology, integrating these technologies to innovate the smart grid (SG) further is future development direction of the power grid. Driven by this trend, billions of devices in the SG are connected to the Internet and generate a large amount of data at network edge. To reduce pressure of cloud computing and overcome defects of centralized learning, emergence of edge computing (EC) makes the computing task transfer from the network center to the network edge. When further exploring the relationship between EC and AI, edge intelligence (EI) has become one of the research hotspots. Advantages of EI in flexibly utilizing EC resources and improving AI model learning efficiency make its application in SG a good prospect. However, since only a few existing studies have applied EI to SG, this paper focuses on the application potential of EI in SG. First, the concepts, characteristics, frameworks, and key technologies of EI are investigated. Then, a comprehensive review of AI and EC applications in SG is presented. Furthermore, application potentials for EI in SG are explored, and four application scenarios of EI for SG are proposed. Finally, challenges and future directions for EI in SG are discussed. This application survey of EI on SG is carried out before EI enters the large-scale commercial stage to provide references and guidelines for developing future EI frameworks in the SG paradigm.
A87: ORI-048 | B87: Web of Science | C87: 1 | D87: Edge Offloading in Smart Grid | E87: Arcas, GI; Cioara, T; Anghel, I; Lazea, D; Hangan, A | F87: 2024 | G87: JOUR | H87: SMART CITIES | I87: 10.3390/smartcities7010028 | J87: Exclude | K87: Not an eligible review/survey publication | L87: Historical eligibility assessment | M87: The historical title/abstract versus full-text split was not retained; reason reconstructed from the final scope and available record metadata. | N87: wos_final.ris
A88: ORI-150 | B88: IEEE Xplore | C88: 1 | D88: Edge-Cloud Architectures for Hybrid Energy Management Systems: A Comprehensive Review | E88: O. Boiko; A. Komin; R. Malekian; P. Davidsson | F88: 2024 | G88: JOUR | H88: IEEE Sensors Journal | I88: 10.1109/jsen.2024.3382390 | J88: Exclude | K88: Reinforcement learning is not the central review subject | L88: Historical eligibility assessment | M88: The historical title/abstract versus full-text split was not retained; reason reconstructed from the final scope and available record metadata. | N88: ieee_final.ris | O88: This article provides an overview of recent research on edge-cloud architectures in hybrid energy management systems (HEMSs). It delves into the typical structure of an IoT system, consisting of three key layers: the perception layer, the network layer, and the application layer. The edge-cloud architecture adds two more layers: the middleware layer and the business layer. This article also addresses challenges in the proposed architecture, including standardization, scalability, security, privacy, regulatory compliance, and infrastructure maintenance. Privacy concerns can hinder the adoption of HEMS. Therefore, we also provide an overview of these concerns and recent research on edge-cloud solutions for HEMS that addresses them. This article concludes by discussing the future trends of edge-cloud architectures for HEMS. These trends include increased use of artificial intelligence on an edge level to improve the performance and reliability of HEMS and the use of blockchain to improve the security and privacy of edge-cloud computing systems.
A89: ORI-158 | B89: IEEE Xplore | C89: 1 | D89: Electric Vehicle Integration With Grid-Forming Capability in Renewable-Powered Microgrids: A Survey and Future Perspectives | E89: M. Osman; I. Serban | F89: 2026 | G89: JOUR | H89: IEEE Access | I89: 10.1109/access.2026.3682011 | J89: Exclude | K89: Reinforcement learning is not the central review subject | L89: Historical eligibility assessment | M89: The historical title/abstract versus full-text split was not retained; reason reconstructed from the final scope and available record metadata. | N89: ieee_final.ris | O89: In recent years, electric vehicles (EVs) are increasingly recognized as flexible energy resources that can provide ancillary services to renewable energy sources-based microgrids (MGs), particularly when operated under grid-forming (GFM) control techniques. However, realizing this potential requires developments across several layers, including EV charger architectures, storage systems coordination, and hierarchical MG control. This paper brings these developments together. It reviews recent advancements in hybrid energy storage systems, converter topologies for on-board and off-board EV chargers, advanced control and energy management systems, vehicle-to-grid implementations, and EV-interactive MG operation. It also provides a comparative assessment of three proposed GFM-based EV-MG integration schemes in terms of GFM resource availability, active power exchange capacity, efficiency, infrastructure cost, and ancillary service potential. Major open research challenges and promising directions are discussed at the end.
A90: ORI-043 | B90: Web of Science | C90: 1 | D90: Emerging Information Technologies for the Energy Management of Onboard Microgrids in Transportation Applications | E90: Huang, Z; Xiao, XC; Gao, Y; Xia, YH; Dragicevic, T; Wheeler, P | F90: 2023 | G90: JOUR | H90: ENERGIES | I90: 10.3390/en16176269 | J90: Exclude | K90: Not an eligible review/survey publication | L90: Historical eligibility assessment | M90: The historical title/abstract versus full-text split was not retained; reason reconstructed from the final scope and available record metadata. | N90: wos_final.ris
A91: ORI-146 | B91: IEEE Xplore | C91: 1 | D91: Energy Management of Battery–Supercapacitor Hybrid Storage in Electric Vehicles With Solar Integration: A Review | E91: I. A. Sayed; Y. Mahmoud | F91: 2025 | G91: JOUR | H91: IEEE Access | I91: 10.1109/access.2025.3636410 | J91: Exclude | K91: Reinforcement learning is not the central review subject | L91: Historical eligibility assessment | M91: The historical title/abstract versus full-text split was not retained; reason reconstructed from the final scope and available record metadata. | N91: ieee_final.ris | O91: Hybrid energy storage systems (HESS) integrating batteries and supercapacitors offer a promising solution to overcome the limitations of battery-only architectures in electric vehicles (EVs). By leveraging the high energy density of batteries and the high power density of supercapacitors, HESS can enhance power delivery, improve energy efficiency, and extend battery lifespan. The effectiveness of HESS, however, is largely determined by the energy management system (EMS) that coordinates power flow under dynamic driving conditions. Unlike existing reviews, this work addresses common gaps in the literature, including the lack of industrial energy storage component examples, limited coverage of recently developed EMS strategies, and insufficient analysis of renewable energy integration. This paper presents a comprehensive review of energy systems in EVs, focusing on EMS strategies and solar PV integration for battery–supercapacitor HESS. Rule-based, optimization-based, model predictive control (MPC), fuzzy logic control (FLC), and reinforcement learning (RL) methods are investigated and compared in terms of control performance, computational cost, adaptability, and real-time feasibility. The review also identifies research gaps and outlines future directions, emphasizing the need for intelligent, adaptive, and multi-objective EMS frameworks for next-generation EVs.
A92: ORI-127 | B92: IEEE Xplore | C92: 1 | D92: Energy Management of Multi-Energy Communities: A Hierarchical MIQP-Constrained Deep Reinforcement Learning Approach | E92: A. S. Omar; R. El-Shatshat | F92: 2025 | G92: JOUR | H92: IEEE Transactions on Sustainable Energy | I92: 10.1109/tste.2025.3550563 | J92: Exclude | K92: Not an eligible review/survey publication | L92: Historical eligibility assessment | M92: The historical title/abstract versus full-text split was not retained; reason reconstructed from the final scope and available record metadata. | N92: ieee_final.ris | O92: This paper proposes a hybrid mixed-integer quadratic programming-constrained deep reinforcement learning (MIQP-CDRL) framework for energy management of multi-energy communities. The framework employs a hierarchical two-layer structure: the MIQP layer handles day-ahead scheduling, minimizing operational costs while ensuring system constraint satisfaction, while the CDRL agent makes real-time adjustments. The goal of this framework is to combine the strengths of CDRL in addressing sequential decision-making problems in stochastic systems with the advantages of a mathematical programming model to guide the agent's exploration during the training and reduce the dependency on opaque policies during real-time operation. The system dynamics are modeled as a constrained Markov decision process (CMDP), which is solved by a model-free CDRL agent built upon the constrained policy optimization (CPO) algorithm. Practical test results demonstrate the effectiveness of this framework in improving the optimality and feasibility of the real-time solutions compared to existing stand-alone DRL approaches.
A93: ORI-036 | B93: Web of Science | C93: 1 | D93: Energy Management Strategies for Hybrid Electric Vehicles: A Technology Roadmap | E93: Mittal, V; Shah, RJ | F93: 2024 | G93: JOUR | H93: WORLD ELECTRIC VEHICLE JOURNAL | I93: 10.3390/wevj15090424 | J93: Exclude | K93: Not an eligible review/survey publication | L93: Historical eligibility assessment | M93: The historical title/abstract versus full-text split was not retained; reason reconstructed from the final scope and available record metadata. | N93: wos_final.ris
A94: ORI-122 | B94: IEEE Xplore | C94: 1 | D94: Energy Management Systems and Strategies in Buildings Sector: A Scoping Review | E94: A. M. Al-Ghaili; H. Kasim; N. M. Al-Hada; B. N. Jørgensen; M. Othman; J. Wang | F94: 2021 | G94: JOUR | H94: IEEE Access | I94: 10.1109/access.2021.3075485 | J94: Exclude | K94: Reinforcement learning is not the central review subject | L94: Historical eligibility assessment | M94: The historical title/abstract versus full-text split was not retained; reason reconstructed from the final scope and available record metadata. | N94: ieee_final.ris | O94: Energy management systems in buildings (EMSs-in-Bs) play key roles in energy saving and management to which an efficient energy management system in buildings (EMS-in-Bs) design contributes. Different scope-based designs of EMS-in-Bs are reviewed. The objective is to highlight different scope-based designs of EMS-in-Bs in which scopes of reviewed papers aim to implement a function of, for example, “monitor energy performance”, “estimate energy-use”, or “control energy-use”. This paper aims to constitute a comprehensive conception of how efficient such an EMS-in-Bs to perform more than one scope (i.e., function). Meaning, is the proposed EMS-in-Bs able to perform several sequential functions? This paper's contribution is to give a function-focused EMS's review utilizing the scope of reviewed papers. That is, reviewed papers are classified based on the scope/function the selected EMS-in-Bs is designed for. This could help select an EMS-in-Bs to perform certain scope/function(s). Another contribution is that, numerous EMSs-in-Bs are reviewed in a classified way so that the most adequate EMS-in-Bs for a certain scenario considering the performed scopes/functions e.g., “monitor” are highlighted. Findings showed that “control-optimize”-functioned EMS-in-Bs achieved highest energy-saving rates ~30% compared to “estimate-predict” with 10%. Findings, insights given by reviewed studies, current problems faced, future directions, and remarks are drawn in conclusion. Analysis done on reviewed papers has found that the highest and lowest averaged-energy saving rates were obtained with papers whose their scopes are implementing “control”-with-“optimize” and “estimate”-with-“predict”, respectively. Energy saving rates for these two classes of scopes have been equal to 22.57% and 10%, respectively. We recommend that there is a need to enhance the estimation- and prediction-related EMS-in-Bs to achieve a higher energy saving rate.
A95: ORI-143 | B95: IEEE Xplore | C95: 1 | D95: Energy Management Systems for Electrified Powertrains: State-of-the-Art Review and Future Trends | E95: A. Biswas; A. Emadi | F95: 2019 | G95: JOUR | H95: IEEE Transactions on Vehicular Technology | I95: 10.1109/tvt.2019.2914457 | J95: Exclude | K95: Reinforcement learning is not the central review subject | L95: Historical eligibility assessment | M95: The historical title/abstract versus full-text split was not retained; reason reconstructed from the final scope and available record metadata. | N95: ieee_final.ris | O95: Energy management systems (EMSs), implemented in the electronic control unit (ECU) of an actual vehicle with electrified powertrain, are a much simpler version of the theoretically developed EMS. Such simplification is done to accommodate the EMS within the given memory constraint and computational capacity of the ECU. The simplification should ensure reasonable performance compared to theoretical EMS under real-life driving scenarios. The process of simplification must be effective to create a versatile and utilitarian EMS. Hence, it is comprised of rigorous analysis of results obtained from theoretical EMS under various driving scenarios. This review paper broadly categorizes most of the reported utilitarian EMSs into three major categories and discusses the processes of simplification associated with each category. The utilitarian EMSs are classified based on their dependence on either online computation or offline pre-computation or even both for spewing control decisions. The paper delineates the chronological steps of a utilitarian EMS development, starting from theoretical background, process of simplification, validation through model-in-the-loop, software-in-the-loop, hardware-in-the-loop simulation, dynamometer test, and on-road performance validation. Future trends of on-board EMSs are also discussed before the conclusion.
A96: ORI-001 | B96: Web of Science; ScienceDirect | C96: 2 | D96: Energy modelling and control of building heating and cooling systems with data-driven and hybrid models—A review | E96: Balali, Yasaman; Chong, Adrian; Busch, Andrew; O’Keefe, Steven | F96: 2023 | G96: JOUR | H96: Renewable and Sustainable Energy Reviews | I96: 10.1016/j.rser.2023.113496 | J96: Exclude | K96: Reinforcement learning is not the central review subject | L96: Historical eligibility assessment | M96: The historical title/abstract versus full-text split was not retained; reason reconstructed from the final scope and available record metadata. | N96: wos_final.ris; ScienceDirect_citations_1783952383784(1).ris
A97: ORI-072 | B97: ScienceDirect | C97: 1 | D97: Enhancing GIS models for sustainable development in human settlements using intelligent IoT infrastructure and human-machine interaction | E97: Xu, Mingxing | F97: 2025 | G97: JOUR | H97: Results in Engineering | I97: 10.1016/j.rineng.2025.106713 | J97: Exclude | K97: Not an eligible review/survey publication | L97: Historical eligibility assessment | M97: The historical title/abstract versus full-text split was not retained; reason reconstructed from the final scope and available record metadata. | N97: ScienceDirect_citations_1783952383784(1).ris | O97: Sustainable development (SD) in human settlements (HS) can be achieved by integrating intelligent IoT infrastructure and human-machine interaction (HMI) into geographic information system (GIS) models. This study proposes a method combining real-time (RT) data and automation to address gaps in technology and urban planning. Current GIS models are ineffective due to limited RT data integration, poor urban system interaction, and lack of adaptability to dynamic changes. These shortcomings hinder sustainable urban growth, leading to suboptimal planning and resource management (RM). The proposed IoT-based framework for SD in HS (IoT-SD-HS) utilizes IoT devices and sensors to collect RT social, economic, and environmental data. This data enables adaptive decision-making (DM), smarter city planning, improved RM, and enhanced urban resilience. Intuitive HMI interfaces allow stakeholders to work effectively with the framework, facilitating data-driven decisions for urban planning and sustainability. Outcomes demonstrate significant improvements in energy consumption (EC), waste management (WM), and infrastructure development. The IoT-SD-HS model achieves high urban resilience (96.12%), WM efficiency (97.34%), and decision accuracy (98.12%), while reducing EC by 10.12%. By continuously evaluating power distribution during peak hours, smart cities reduce carbon footprints and save costs, demonstrating superior performance compared to existing methods. © 2012 Published by Elsevier Ltd. Selection and/or peer-review under responsibility of Global Science and Technology Forum Pte Ltd
A98: ORI-154 | B98: IEEE Xplore | C98: 1 | D98: Evolutionary Game Theory as a Catalyst in Smart Grids: From Theoretical Insights to Practical Strategies | E98: A. Karaki; L. Al-Fagih | F98: 2024 | G98: JOUR | H98: IEEE Access | I98: 10.1109/access.2024.3436935 | J98: Exclude | K98: Not an eligible review/survey publication | L98: Historical eligibility assessment | M98: The historical title/abstract versus full-text split was not retained; reason reconstructed from the final scope and available record metadata. | N98: ieee_final.ris | O98: The increase in the installation of distributed energy resources (DERs) globally has led to a remarkable transformation in the structure of smart grids due to the growing number of energy participants. Recently, electricity markets (EM) have received substantial attention as a viable solution for the complex issue of managing DERs. Modeling the power grid as a complex system of interacting components facilitates investigating the interaction among electricity producers and consumers to maintain the total generation and demand at a balance. In this work, we present a review of the recent advances in adopting evolutionary game theory (EGT), to mitigate challenges in the emerging smart grid, as a decision-making framework for trading dynamics and considering large populations. It includes a taxonomy of various EGT applications in energy trading dynamics, DER management, and policy and infrastructure development. Finally, the linkage between multi-agent reinforcement learning (MARL) and EGT is provided, highlighting their mathematical parallels in the context of smart grid applications.
A99: ORI-166 | B99: IEEE Xplore | C99: 1 | D99: Evolving Electric Mobility Energy Efficiency: In-Depth Analysis of Integrated Electronic Control Unit Development in Electric Vehicles | E99: S. S. A. Naqvi; H. Jamil; N. Iqbal; S. Khan; M. A. Khan; F. Qayyum; D. -H. Kim | F99: 2024 | G99: JOUR | H99: IEEE Access | I99: 10.1109/access.2024.3356598 | J99: Exclude | K99: Not an eligible review/survey publication | L99: Historical eligibility assessment | M99: The historical title/abstract versus full-text split was not retained; reason reconstructed from the final scope and available record metadata. | N99: ieee_final.ris | O99: The integrated Electronic Control Unit (ECU) plays a pivotal role in optimizing energy efficiency within electric vehicles (EVs) by coordinating various subsystems, including the Vehicle Control Unit (VCU), Electrical Power Steering (EPS), Electronic Stability Control (ESC), and Body Control Unit (BCU). Our comprehensive review deeply explores the various aspects of integrated ECUs and their sub-disciplines, emphasizing development approaches and algorithms specifically designed for mobility energy efficiency. The study shows the effect of various control units on energy efficiency by carefully examining case studies and real-world applications. Employing a critical assessment, the paper examines the advantages and disadvantages of various control systems utilized in electric vehicles (EVs), providing insight into their effectiveness in various situations. The presented study is typically related to the relationship between ECUs and their sub-branches through an integrated approach. By comparing current control approaches, the study offers a deep knowledge of the role of these units in improving vehicle performance, stability, and overall control. Furthermore, we evaluate the strengths and limitations of integrated ECU algorithms in the context of EV control by comparing them in a fair amount of detail. We identify important research gaps by integrating knowledge of multiple control areas in EV. The research effort will give researchers a path forward and make it possible to pinpoint the prospective dimensions that need further exploration in advancing the area of integrated ECUs in EVs.
A100: ORI-118 | B100: ScienceDirect | C100: 1 | D100: Exploring the comprehensive integration of artificial intelligence in optimizing HVAC system operations: A review and future outlook | E100: Lu, Shengze; Zhou, Shiyu; Ding, Yan; Kim, Moon Keun; Yang, Bin; Tian, Zhe; Liu, Jiying | F100: 2025 | G100: JOUR | H100: Results in Engineering | I100: 10.1016/j.rineng.2024.103765 | J100: Exclude | K100: Reinforcement learning is not the central review subject | L100: Historical eligibility assessment | M100: The historical title/abstract versus full-text split was not retained; reason reconstructed from the final scope and available record metadata. | N100: ScienceDirect_citations_1783952383784(1).ris | O100: With the rapid development of the artificial intelligence (AI) technology, its application in optimizing heating, ventilation and air-conditioning (HVAC) systems operation is becoming increasingly widespread. This study reviews the latest advances in AI optimization for HVAC systems operation, systematically outlining the characteristics of the AI technology and its various application methods in air conditioning systems. The main features of the AI technology are first introduced. The main algorithms of supervised learning, reinforcement learning, and deep learning are then analyzed in the fields of air conditioning operation optimization, energy consumption prediction and control, indoor environmental protection, and fault detection and diagnosis. The combination of the AI and digital twin technologies is also explored. This review study focuses on the intelligent control technology, multi-objective optimization of system operation, system optimization based on occupant behavior and thermal comfort, and system fault detection and diagnosis. Although the AI technology has led to satisfactory results in air conditioning system optimization, its practical applications still face challenges, such as the model accuracy and generalization ability, applicability, and integration with existing systems. The analysis conducted in this paper provides a foundation for the optimization of HVAC system operation.
A101: ORI-079 | B101: ScienceDirect | C101: 1 | D101: Exploring three pillars of construction robotics via dual-track quantitative analysis | E101: Liu, Yuming; Alias, Aidi Hizami Bin; Haron, Nuzul Azam; Bakar, Nabilah Abu; Wang, Hao | F101: 2024 | G101: JOUR | H101: Automation in Construction | I101: 10.1016/j.autcon.2024.105391 | J101: Exclude | K101: Not an eligible review/survey publication | L101: Historical eligibility assessment | M101: The historical title/abstract versus full-text split was not retained; reason reconstructed from the final scope and available record metadata. | N101: ScienceDirect_citations_1783952383784(1).ris | O101: Construction robotics has emerged as a leading technology in the construction industry. This paper conducts an innovative dual-track quantitative comprehensive method to analyze the current literature and assess future trends. First, a bibliometric review of 955 journal articles published between 1974 and 2023 was performed, exploring keywords, journals, countries, and clusters. Furthermore, a neural topic model based on BERTopic addresses topic modeling repetition issues. The study identifies building information modeling (BIM), human–robot collaboration (HRC), and deep reinforcement learning (DRL) as “three pillars” in the field. Additionally, we systematically reviewed the relevant literature and nested symbiotic relationships. The outcome of this study is twofold: first, the findings provide quantitative and qualitative scientific guidance for future research on trends; second, the innovative dual-track quantitative analysis research methodology simultaneously stimulates critical thinking about the modeling of other similarly trending topics characterized to avoid high degree of homogeneity and corpus overlap.
...

Sheet Sensitivity 87
A1: Expanded Sensitivity Search — 87 Unique Records
A3: Sensitivity ID | B3: Sources | C3: Source count | D3: Title | E3: Authors | F3: Year | G3: Type | H3: Publication | I3: DOI | J3: Original 172 match | K3: Current corpus match | L3: Screening decision | M3: Primary exclusion reason | N3: Notes | O3: Occurrence count | P3: Source files | Q3: Abstract
A4: SENS-004 | B4: WoS | C4: 1 | D4: A Comprehensive Literature Review of Optimization Algorithms for Intelligent Load Scheduling in Home Energy Management Systems | E4: Durlik, F; Grela, J; Laton, D | F4: 2026 | G4: JOUR | H4: ENERGIES | I4: 10.3390/en19112517 | J4: No | K4: No | L4: Excluded | M4: Reinforcement learning is not the central review subject | N4: Title/abstract screening | O4: 1 | P4: wos_expanded.ris | Q4: The increasing complexity of residential energy systems, driven by rising electricity demand, renewable energy integration, and dynamic pricing mechanisms, has intensified the need for intelligent load scheduling within Home Energy Management Systems (HEMSs). This paper presents a comprehensive literature review of optimization algorithms applied to residential load scheduling, based on an analysis of 78 peer-reviewed studies published between 2020 and 2025. The analysis reveals a clear shift from conventional deterministic optimization toward adaptive and data-driven approaches capable of operating in uncertain and dynamic environments. Metaheuristic methods are widely used for solving complex scheduling problems, while Machine Learning and Deep Learning (DL) techniques primarily support forecasting tasks related to energy demand and renewable generation. Reinforcement Learning (RL) and Deep Reinforcement Learning (DRL) approaches enable autonomous real-time decision-making, although challenges related to scalability, computational cost, and practical deployment remain unresolved. The review identifies hybrid architectures that combine forecasting, optimization, and control mechanisms as the most promising direction for future HEMS development. Finally, the paper highlights key research gaps, including limited real-world validation, insufficient consideration of physical infrastructure constraints, and the need for scalable distributed control frameworks for future smart grids and energy communities.
A5: SENS-026 | B5: WoS; SD A | C5: 2 | D5: A comprehensive review and framework on the applications of digital twins for energy transition at the district level | E5: Jalilzadeh, A; Rafiee, A; van Oosterom, P; Konstantinou, T | F5: 2026 | G5: JOUR | H5: RENEWABLE & SUSTAINABLE ENERGY REVIEWS | I5: 10.1016/j.rser.2026.116872 | J5: No | K5: No | L5: Excluded | M5: Reinforcement learning is not the central review subject | N5: Title/abstract screening | O5: 2 | P5: wos_expanded.ris; ScienceDirect_citations_1788180573805_searchA.ris | Q5: Districts face dual pressures: reducing carbon emissions while managing surging electricity demand from electrification and urban growth. Traditional grid expansion cannot match the speed and complexity required for modern energy transitions. District energy transitions require connecting different scales, from individual buildings to grid networks, and different timeframes, from daily operations to long-term planning. Despite growing interest in Digital Twin (DT) for energy management, their application to integrated district-level energy transitions remains poorly understood. This review investigates how DTs can enable district energy transitions by examining their applications in built environment and energy infrastructure at district level, analyzing implementations across Positive Energy Districts (PEDs), microgrids (MGs), and related district energy paradigms. DT components (physical models, core capabilities, data infrastructure, and functional evolution) are investigated to assess their integrative potential. The analysis reveals three disconnects: building and grid systems are modeled separately despite inherent interdependencies; operational insights rarely inform infrastructure planning; and intervention strategies overlook sequential dependencies. To address these gaps, we propose an integrated framework advancing DTs toward district energy planning. The framework bridges semantic, temporal, and sequential planning through: knowledge graph architectures enabling cross-domain data integration, coupled simulation pipelines capturing building-grid interactions, and reinforcement learning optimizing intervention sequences. Unlike optimization that fixes strategies upfront, sequential planning accommodates technology emergence and regulatory shifts inherent to multi-decade transitions. This integrated approach transforms DTs from domain-specific monitoring tools into strategic planning platforms where coordinated building improvements and distributed energy resources defer costly grid expansions while accelerating district decarbonization.
A6: SENS-050 | B6: WoS | C6: 1 | D6: A comprehensive review of AI-driven approaches for smart grid stability and reliability | E6: Ahmadi, M; Aly, H; Gu, JS | F6: 2026 | G6: JOUR | H6: RENEWABLE & SUSTAINABLE ENERGY REVIEWS | I6: 10.1016/j.rser.2025.116424 | J6: No | K6: No | L6: Excluded | M6: Reinforcement learning is not the central review subject | N6: Title/abstract screening | O6: 1 | P6: wos_expanded.ris | Q6: The stability and reliability of smart grids are essential for ensuring efficient and secure electricity delivery, particularly amid the increasing integration of renewable energy sources. This review presents a comprehensive analysis of artificial intelligence (AI)-based methods for real-time grid management, and fault detection. Unlike previous works that focus on isolated grid functions, this study provides a unified framework encompassing energy monitoring and control, optimization, and resilience. Machine learning, deep learning, and reinforcement learning techniques are systematically evaluated across diverse grid tasks, highlighting their strengths, limitations, and implementation challenges. Special attention is given to hybrid models that combine AI with optimization strategies to address issues such as scalability, computational complexity, and adaptability. The paper identifies critical research gaps and offers actionable recommendations to advance AI-driven smart grid operations, promoting more resilient, adaptive, and intelligent power systems.
A7: SENS-067 | B7: SD B | C7: 1 | D7: A comprehensive review of deep reinforcement learning applications from centralized power generation to modern energy internet frameworks | E7: Mahmud, Sakib; Sayed, Aya Nabil; Himeur, Yassine; Nhlabatsi, Armstrong; Bensaali, Faycal | F7: 2026 | G7: JOUR | H7: Renewable and Sustainable Energy Reviews | I7: 10.1016/j.rser.2025.116481 | J7: No | K7: No | L7: Excluded | M7: Building control is not the central application domain | N7: Title/abstract screening | O7: 1 | P7: ScienceDirect_citations_1788180526175_search_B.ris | Q7: The energy internet (EI) is evolving toward decentralized, data-rich, and time-critical operation, where legacy optimization often fails to meet complexity, scalability, and real-time constraints. Deep reinforcement learning (DRL) offers a data-driven alternative that couples perception with sequential decision-making. This review synthesizes evidence from more than 500 peer-reviewed studies published between 2020 and 2026, mapping DRL applications across distributed generation, transmission, distribution, energy storage systems, energy markets, local energy management, grid security, and data privacy. We present a structured taxonomy covering value-based, policy-based, actor-critic, model-based, and advanced multi-agent and multi-objective approaches, and link algorithms to tasks such as dispatch, microgrid coordination, real-time pricing, load balancing, and demand–response. Reported benefits include energy savings, emissions reduction, and improved operational efficiency, although gains are often contingent on data quality, reward design, and benchmark selection. Persistent challenges include dataset scarcity and bias, limited generalization across assets and seasons, computational cost, safety and constraint handling, and the gap between simulation and field deployment. We identify promising directions: hybrid model-free and model-based DRL, offline-to-online learning, transfer and meta-learning for rapid adaptation, integration with federated learning and blockchain for privacy and trust, and progress in interpretability, uncertainty quantification, and formal safety guarantees. The review consolidates a fragmented literature, surfaces unresolved issues, and outlines practical research pathways for building reliable, sustainable, and resilient EI solutions with DRL.
A8: SENS-077 | B8: IEEE | C8: 1 | D8: A Comprehensive Review of Machine Learning Techniques for Enhancing Energy Efficiency in Renewable Integrated Smart Grids | E8: R. Goswami; R. Roy; K. K. Mandal | F8: 2025 | G8: CONF | H8: 2025 International Conference on Power Electronics and Energy (ICPEE) | I8: 10.1109/icpee65973.2025.11411031 | J8: No | K8: No | L8: Excluded | M8: Conference paper; core corpus restricted to journal reviews | O8: 1 | P8: IEEE Xplore Citation RIS Download 2026.8.31.15.34.58_expanded_sens.ris | Q8: Modern smart grids integrate renewable energy sources, energy storage, and intelligent control systems to enhance efficiency, reliability, and sustainability. Machine learning (ML) serves as a critical enabler of these improvements by facilitating more effective energy flow coordination and increasing demand-side flexibility. This review explores advanced ML methodologies aimed at boosting energy efficiency and optimizing demand response in power systems with substantial renewable integration. Core applications include forecasting of load and renewable generation, demand-side management, storage system optimization, and anomaly detection-utilizing models such as neural networks, support vector machines, ensemble learning, and reinforcement learning. The paper also examines key challenges such as limited data availability, high computational demands, cybersecurity risks, and regulatory constraints. Realworld implementations and pilot projects illustrate the practical advantages and expanding use of ML in utility operations. The review concludes that, although ML holds great promise, realizing its full potential requires overcoming significant technical and institutional challenges through interdisciplinary collaboration and supportive policy frameworks.
A9: SENS-041 | B9: WoS | C9: 1 | D9: A Comprehensive Review of Option Value in Energy Economics | E9: Giannelos, S; Pudjianto, D; Bellizio, F; Qiu, DW; Strbac, G | F9: 2025 | G9: JOUR | H9: IET RENEWABLE POWER GENERATION | I9: 10.1049/rpg2.70122 | J9: No | K9: No | L9: Excluded | M9: Reinforcement learning is not the central review subject | N9: Title/abstract screening | O9: 1 | P9: wos_expanded.ris | Q9: This review examines the economic concept of option value for the economic integration of renewables in power systems, considering energy markets' distinctive characteristics. Energy markets exhibit limited storability, price volatility, seasonality patterns, and network constraints that necessitate specialised valuation approaches beyond traditional financial models. We provide a comprehensive analysis of methodologies ranging from conventional financial techniques-Black-Scholes models, binomial trees, Monte Carlo simulation, and partial differential equations-to advanced computational approaches including stochastic optimisation, machine learning, and reinforcement learning. The paper explores how real options theory provides a framework for quantifying the value of flexibility in power systems. Emphasis is placed on smart technologies, whose option value stems from their ability to defer or displace conventional investments under uncertainty. We discuss how stochastic optimisation effectively captures the sequential decision-making characteristic of real options in energy systems. The review highlights emerging applications of machine learning and reinforcement learning for valuing energy derivatives and flexibility options, addressing computational challenges of high-dimensional problems. Finally, we identify promising research directions, including integrated physical-financial modelling frameworks, advanced computational methods, and agent-based approaches for capturing strategic behaviour in evolving energy markets characterised by increasing decarbonisation, digitalisation, and decentralisation.
A10: SENS-058 | B10: WoS; SD B | C10: 2 | D10: A critical review of field implementation of data-driven operation and maintenance technologies to reduce building energy use and GHG emissions | E10: Gunay, B; Markus, A; Parsaei, A; Darwazeh, D; Bursill, J; Pellerin, L | F10: 2025 | G10: JOUR | H10: ENERGY AND BUILDINGS | I10: 10.1016/j.enbuild.2025.116087 | J10: Yes | K10: Possible/previously screened | L10: Previously screened | M10: Matched to original 172-record search set | N10: Not rescreened | O10: 2 | P10: wos_expanded.ris; ScienceDirect_citations_1788180526175_search_B.ris | Q10: Field implementation studies spanning six data-driven building operation and maintenance (DBOM) application domains (model-based predictive control (MPC), occupant-centric control (OCC), automated demand response (ADR), reinforcement learning control (RLC), fault detection and diagnostics (FDD), and virtual metering (VM)) were reviewed. The review aimed to make inter- and intra-application domain comparisons in terms of implementation processes and outcomes. The studies were classified by different levels of integration effort and sensing infrastructure complexity according to the quantity and kind of their inputs and outputs. An analysis is conducted on how energy-related success metrics (e.g., energy use, cost, demand) correlate with the integration effort and the complexity of the infrastructure. In general, MPC and ADR studies were found to require a higher level of integration effort than OCC studies; yet, OCC studies tend to require upgrades in the sensing infrastructure, unlike MPC and ADR studies. 95% of those reporting post-implementation energy metrics achieved more than 10% improvement in their energy-related objectives. The analysis results also highlight that a large fraction of the FDD and VM studies did not follow a measurement and verification procedure to quantify energy-related performance improvements upon field implementation. 90% of the papers did not include feedback from building operators or occupants after the implementation.
A11: SENS-009 | B11: WoS; IEEE | C11: 2 | D11: A Review of Deep Reinforcement Learning for Smart Building Energy Management | E11: Yu, L; Qin, SQ; Zhang, M; Shen, C; Jiang, T; Guan, XH | F11: 2021 | G11: JOUR | H11: IEEE INTERNET OF THINGS JOURNAL | I11: 10.1109/jiot.2021.3078462 | J11: Yes | K11: Possible/previously screened | L11: Previously screened | M11: Matched to original 172-record search set | N11: Not rescreened | O11: 2 | P11: wos_expanded.ris; IEEE Xplore Citation RIS Download 2026.8.31.15.34.58_expanded_sens.ris | Q11: Global buildings account for about 30% of the total energy consumption and carbon emission, raising severe energy and environmental concerns. Therefore, it is significant and urgent to develop novel smart building energy management (SBEM) technologies for the advance of energy efficient and green buildings. However, it is a nontrivial task due to the following challenges. First, it is generally difficult to develop an explicit building thermal dynamics model that is both accurate and efficient enough for building control. Second, there are many uncertain system parameters (e.g., renewable generation output, outdoor temperature, and the number of occupants). Third, there are many spatially and temporally coupled operational constraints. Fourth, building energy optimization problems can not be solved in real time by traditional methods when they have extremely large solution spaces. Fifthly, traditional building energy management methods have respective applicable premises, which means that they have low versatility when confronted with varying building environments. With the rapid development of Internet of Things technology and computation capability, artificial intelligence technology find its significant competence in control and optimization. As a general artificial intelligence technology, deep reinforcement learning (DRL) is promising to address the above challenges. Notably, the recent years have seen the surge of DRL for SBEM. However, there lacks a systematic overview of different DRL methods for SBEM. To fill the gap, this article provides a comprehensive review of DRL for SBEM from the perspective of system scale. In particular, we identify the existing unresolved issues and point out possible future research directions.
